<TextureAtlas imagePath="sprites.png">
	<SubTexture name="Attack-Down-1.png" x="0" y="35" width="30" height="21"/>
	<SubTexture name="Attack-Left-1.png" x="31" y="35" width="23" height="19"/>
	<SubTexture name="Attack-Right-1.png" x="30" y="57" width="23" height="19"/>
	<SubTexture name="Attack-Up-1.png" x="78" y="0" width="21" height="32"/>
	<SubTexture name="Hurt-Down-1.png" x="0" y="0" width="32" height="17"/>
	<SubTexture name="Hurt-Left-1.png" x="0" y="92" width="26" height="18"/>
	<SubTexture name="Hurt-Right-1.png" x="27" y="92" width="26" height="18"/>
	<SubTexture name="Hurt-Up-1.png" x="0" y="18" width="32" height="16"/>
	<SubTexture name="Idle-Down-1.png" x="55" y="22" width="22" height="21"/>
	<SubTexture name="Idle-Down-2.png" x="54" y="95" width="22" height="22"/>
	<SubTexture name="Idle-Down-3.png" x="77" y="44" width="22" height="23"/>
	<SubTexture name="Idle-Down-4.png" x="54" y="95" width="22" height="22"/>
	<SubTexture name="Idle-Left-1.png" x="100" y="0" width="20" height="21"/>
	<SubTexture name="Idle-Left-2.png" x="56" y="0" width="21" height="20"/>
	<SubTexture name="Idle-Left-3.png" x="54" y="75" width="22" height="19"/>
	<SubTexture name="Idle-Left-4.png" x="56" y="0" width="21" height="20"/>
	<SubTexture name="Idle-Right-1.png" x="77" y="89" width="20" height="21"/>
	<SubTexture name="Idle-Right-2.png" x="77" y="68" width="21" height="20"/>
	<SubTexture name="Idle-Right-3.png" x="54" y="55" width="22" height="19"/>
	<SubTexture name="Idle-Right-4.png" x="77" y="68" width="21" height="20"/>
	<SubTexture name="Idle-Up-1.png" x="33" y="0" width="22" height="21"/>
	<SubTexture name="Idle-Up-2.png" x="98" y="89" width="20" height="20"/>
	<SubTexture name="Idle-Up-3.png" x="99" y="68" width="20" height="18"/>
	<SubTexture name="Idle-Up-4.png" x="98" y="89" width="20" height="20"/>
	<SubTexture name="Sleep-1.png" x="0" y="57" width="29" height="15"/>
	<SubTexture name="Sleep-2.png" x="0" y="73" width="27" height="18"/>
	<SubTexture name="Walk-Down-1.png" x="55" y="22" width="22" height="21"/>
	<SubTexture name="Walk-Down-2.png" x="54" y="95" width="22" height="22"/>
	<SubTexture name="Walk-Down-3.png" x="77" y="44" width="22" height="23"/>
	<SubTexture name="Walk-Down-4.png" x="54" y="95" width="22" height="22"/>
	<SubTexture name="Walk-Left-1.png" x="100" y="0" width="20" height="21"/>
	<SubTexture name="Walk-Left-2.png" x="56" y="0" width="21" height="20"/>
	<SubTexture name="Walk-Left-3.png" x="54" y="75" width="22" height="19"/>
	<SubTexture name="Walk-Left-4.png" x="56" y="0" width="21" height="20"/>
	<SubTexture name="Walk-Right-1.png" x="77" y="89" width="20" height="21"/>
	<SubTexture name="Walk-Right-2.png" x="77" y="68" width="21" height="20"/>
	<SubTexture name="Walk-Right-3.png" x="54" y="55" width="22" height="19"/>
	<SubTexture name="Walk-Right-4.png" x="77" y="68" width="21" height="20"/>
	<SubTexture name="Walk-Up-1.png" x="33" y="0" width="22" height="21"/>
	<SubTexture name="Walk-Up-2.png" x="98" y="89" width="20" height="20"/>
	<SubTexture name="Walk-Up-3.png" x="99" y="68" width="20" height="18"/>
	<SubTexture name="Walk-Up-4.png" x="98" y="89" width="20" height="20"/>
</TextureAtlas>