<?xml version="1.0"?>
<Pokemon gameVersion="EoS">
	<!--In-game text-->
	<Strings>
		<English>
			<Name>Onix</Name>
			<Category>Rock Snake</Category>
		</English>
	</Strings>
	<!--Primary gender entity-->
	<GenderedEntity>
		<PokeID>95</PokeID>
		<Unk31>55</Unk31>
		<PokedexNumber>95</PokedexNumber>
		<Unk1>1</Unk1>
		<EvolutionReq>
			<PreEvoIndex>0</PreEvoIndex>
			<Method>0</Method>
			<Param1>0</Param1>
			<Param2>0</Param2>
		</EvolutionReq>
		<SpriteIndex>104</SpriteIndex>
		<Gender>1</Gender>
		<BodySize>4</BodySize>
		<PrimaryType>13</PrimaryType>
		<SecondaryType>9</SecondaryType>
		<MovementType>0</MovementType>
		<IQGroup>4</IQGroup>
		<PrimaryAbility>7</PrimaryAbility>
		<SecondaryAbility>13</SecondaryAbility>
		<Bitfield>0x70</Bitfield>
		<ExpYield>108</ExpYield>
		<RecruitRate1>10</RecruitRate1>
		<RecruitRate2>20</RecruitRate2>
		<BaseStats>
			<HP>17</HP>
			<Attack>13</Attack>
			<SpAttack>13</SpAttack>
			<Defense>8</Defense>
			<SpDefense>8</SpDefense>
		</BaseStats>
		<Weight>358</Weight>
		<Size>76</Size>
		<Unk17>0xa</Unk17>
		<Unk18>0xa</Unk18>
		<Unk19>0x2</Unk19>
		<Unk20>0x8</Unk20>
		<Unk21>0x64</Unk21>
		<BasePokemonIndex>95</BasePokemonIndex>
		<ExclusiveItems>
			<ItemID>0</ItemID>
			<ItemID>0</ItemID>
			<ItemID>0</ItemID>
			<ItemID>1089</ItemID>
		</ExclusiveItems>
		<Unk27>0x320</Unk27>
		<Unk28>0xf</Unk28>
		<Unk29>0x1e</Unk29>
		<Unk30>0xa</Unk30>
	</GenderedEntity>
	<!--Secondary gender entity-->
	<GenderedEntity>
		<PokeID>95</PokeID>
		<Unk31>55</Unk31>
		<PokedexNumber>95</PokedexNumber>
		<Unk1>1</Unk1>
		<EvolutionReq>
			<PreEvoIndex>0</PreEvoIndex>
			<Method>0</Method>
			<Param1>0</Param1>
			<Param2>0</Param2>
		</EvolutionReq>
		<SpriteIndex>104</SpriteIndex>
		<Gender>2</Gender>
		<BodySize>4</BodySize>
		<PrimaryType>13</PrimaryType>
		<SecondaryType>9</SecondaryType>
		<MovementType>0</MovementType>
		<IQGroup>4</IQGroup>
		<PrimaryAbility>7</PrimaryAbility>
		<SecondaryAbility>13</SecondaryAbility>
		<Bitfield>0x70</Bitfield>
		<ExpYield>108</ExpYield>
		<RecruitRate1>10</RecruitRate1>
		<RecruitRate2>20</RecruitRate2>
		<BaseStats>
			<HP>17</HP>
			<Attack>13</Attack>
			<SpAttack>13</SpAttack>
			<Defense>8</Defense>
			<SpDefense>8</SpDefense>
		</BaseStats>
		<Weight>358</Weight>
		<Size>76</Size>
		<Unk17>0xa</Unk17>
		<Unk18>0xa</Unk18>
		<Unk19>0x2</Unk19>
		<Unk20>0x8</Unk20>
		<Unk21>0x64</Unk21>
		<BasePokemonIndex>95</BasePokemonIndex>
		<ExclusiveItems>
			<ItemID>0</ItemID>
			<ItemID>0</ItemID>
			<ItemID>0</ItemID>
			<ItemID>1089</ItemID>
		</ExclusiveItems>
		<Unk27>0x320</Unk27>
		<Unk28>0xf</Unk28>
		<Unk29>0x1e</Unk29>
		<Unk30>0xa</Unk30>
	</GenderedEntity>
	<!--Moveset from waza_p.bin-->
	<Moveset>
		<!--Learns 17 move(s)-->
		<LevelUpMoves>
			<Learn>
				<Level>1</Level>
				<MoveID>58</MoveID>
			</Learn>
			<Learn>
				<Level>1</Level>
				<MoveID>125</MoveID>
			</Learn>
			<Learn>
				<Level>1</Level>
				<MoveID>154</MoveID>
			</Learn>
			<Learn>
				<Level>3</Level>
				<MoveID>212</MoveID>
			</Learn>
			<Learn>
				<Level>6</Level>
				<MoveID>27</MoveID>
			</Learn>
			<Learn>
				<Level>9</Level>
				<MoveID>28</MoveID>
			</Learn>
			<Learn>
				<Level>14</Level>
				<MoveID>19</MoveID>
			</Learn>
			<Learn>
				<Level>17</Level>
				<MoveID>73</MoveID>
			</Learn>
			<Learn>
				<Level>22</Level>
				<MoveID>141</MoveID>
			</Learn>
			<Learn>
				<Level>25</Level>
				<MoveID>161</MoveID>
			</Learn>
			<Learn>
				<Level>30</Level>
				<MoveID>540</MoveID>
			</Learn>
			<Learn>
				<Level>33</Level>
				<MoveID>342</MoveID>
			</Learn>
			<Learn>
				<Level>38</Level>
				<MoveID>237</MoveID>
			</Learn>
			<Learn>
				<Level>41</Level>
				<MoveID>1</MoveID>
			</Learn>
			<Learn>
				<Level>46</Level>
				<MoveID>143</MoveID>
			</Learn>
			<Learn>
				<Level>49</Level>
				<MoveID>140</MoveID>
			</Learn>
			<Learn>
				<Level>54</Level>
				<MoveID>481</MoveID>
			</Learn>
		</LevelUpMoves>
		<!--Has 7 egg move(s)-->
		<EggMoves>
			<MoveID>30</MoveID>
			<MoveID>105</MoveID>
			<MoveID>121</MoveID>
			<MoveID>155</MoveID>
			<MoveID>194</MoveID>
			<MoveID>302</MoveID>
			<MoveID>350</MoveID>
		</EggMoves>
		<!--Can learn 40 HM/TM move(s)-->
		<HmTmMoves>
			<MoveID>1</MoveID>
			<MoveID>8</MoveID>
			<MoveID>22</MoveID>
			<MoveID>24</MoveID>
			<MoveID>29</MoveID>
			<MoveID>30</MoveID>
			<MoveID>48</MoveID>
			<MoveID>50</MoveID>
			<MoveID>56</MoveID>
			<MoveID>67</MoveID>
			<MoveID>73</MoveID>
			<MoveID>104</MoveID>
			<MoveID>115</MoveID>
			<MoveID>118</MoveID>
			<MoveID>141</MoveID>
			<MoveID>155</MoveID>
			<MoveID>172</MoveID>
			<MoveID>197</MoveID>
			<MoveID>223</MoveID>
			<MoveID>227</MoveID>
			<MoveID>232</MoveID>
			<MoveID>263</MoveID>
			<MoveID>284</MoveID>
			<MoveID>301</MoveID>
			<MoveID>304</MoveID>
			<MoveID>324</MoveID>
			<MoveID>326</MoveID>
			<MoveID>328</MoveID>
			<MoveID>360</MoveID>
			<MoveID>394</MoveID>
			<MoveID>471</MoveID>
			<MoveID>472</MoveID>
			<MoveID>475</MoveID>
			<MoveID>480</MoveID>
			<MoveID>481</MoveID>
			<MoveID>534</MoveID>
			<MoveID>536</MoveID>
			<MoveID>539</MoveID>
			<MoveID>540</MoveID>
			<MoveID>541</MoveID>
		</HmTmMoves>
	</Moveset>
	<!--Moveset from waza_p2.bin-->
	<Moveset>
		<!--Learns 16 move(s)-->
		<LevelUpMoves>
			<Learn>
				<Level>1</Level>
				<MoveID>58</MoveID>
			</Learn>
			<Learn>
				<Level>1</Level>
				<MoveID>125</MoveID>
			</Learn>
			<Learn>
				<Level>1</Level>
				<MoveID>154</MoveID>
			</Learn>
			<Learn>
				<Level>3</Level>
				<MoveID>212</MoveID>
			</Learn>
			<Learn>
				<Level>6</Level>
				<MoveID>27</MoveID>
			</Learn>
			<Learn>
				<Level>9</Level>
				<MoveID>28</MoveID>
			</Learn>
			<Learn>
				<Level>14</Level>
				<MoveID>19</MoveID>
			</Learn>
			<Learn>
				<Level>17</Level>
				<MoveID>73</MoveID>
			</Learn>
			<Learn>
				<Level>22</Level>
				<MoveID>141</MoveID>
			</Learn>
			<Learn>
				<Level>25</Level>
				<MoveID>161</MoveID>
			</Learn>
			<Learn>
				<Level>30</Level>
				<MoveID>540</MoveID>
			</Learn>
			<Learn>
				<Level>33</Level>
				<MoveID>342</MoveID>
			</Learn>
			<Learn>
				<Level>38</Level>
				<MoveID>1</MoveID>
			</Learn>
			<Learn>
				<Level>41</Level>
				<MoveID>143</MoveID>
			</Learn>
			<Learn>
				<Level>46</Level>
				<MoveID>140</MoveID>
			</Learn>
			<Learn>
				<Level>49</Level>
				<MoveID>481</MoveID>
			</Learn>
		</LevelUpMoves>
		<!--Has 7 egg move(s)-->
		<EggMoves>
			<MoveID>30</MoveID>
			<MoveID>105</MoveID>
			<MoveID>121</MoveID>
			<MoveID>155</MoveID>
			<MoveID>194</MoveID>
			<MoveID>302</MoveID>
			<MoveID>350</MoveID>
		</EggMoves>
		<!--Can learn 40 HM/TM move(s)-->
		<HmTmMoves>
			<MoveID>1</MoveID>
			<MoveID>8</MoveID>
			<MoveID>22</MoveID>
			<MoveID>24</MoveID>
			<MoveID>29</MoveID>
			<MoveID>30</MoveID>
			<MoveID>48</MoveID>
			<MoveID>50</MoveID>
			<MoveID>56</MoveID>
			<MoveID>67</MoveID>
			<MoveID>73</MoveID>
			<MoveID>104</MoveID>
			<MoveID>115</MoveID>
			<MoveID>118</MoveID>
			<MoveID>141</MoveID>
			<MoveID>155</MoveID>
			<MoveID>172</MoveID>
			<MoveID>197</MoveID>
			<MoveID>223</MoveID>
			<MoveID>227</MoveID>
			<MoveID>232</MoveID>
			<MoveID>263</MoveID>
			<MoveID>284</MoveID>
			<MoveID>301</MoveID>
			<MoveID>304</MoveID>
			<MoveID>324</MoveID>
			<MoveID>326</MoveID>
			<MoveID>328</MoveID>
			<MoveID>360</MoveID>
			<MoveID>394</MoveID>
			<MoveID>471</MoveID>
			<MoveID>472</MoveID>
			<MoveID>475</MoveID>
			<MoveID>480</MoveID>
			<MoveID>481</MoveID>
			<MoveID>534</MoveID>
			<MoveID>536</MoveID>
			<MoveID>539</MoveID>
			<MoveID>540</MoveID>
			<MoveID>541</MoveID>
		</HmTmMoves>
	</Moveset>
	<!--Stats growth and exp requirements-->
	<StatsGrowth>
		<!--Level 1-->
		<Level>
			<RequiredExp>0</RequiredExp>
			<HP>0</HP>
			<Attack>0</Attack>
			<SpAttack>0</SpAttack>
			<Defense>0</Defense>
			<SpDefense>0</SpDefense>
		</Level>
		<!--Level 2-->
		<Level>
			<RequiredExp>8</RequiredExp>
			<HP>2</HP>
			<Attack>2</Attack>
			<SpAttack>2</SpAttack>
			<Defense>2</Defense>
			<SpDefense>2</SpDefense>
		</Level>
		<!--Level 3-->
		<Level>
			<RequiredExp>21</RequiredExp>
			<HP>2</HP>
			<Attack>2</Attack>
			<SpAttack>2</SpAttack>
			<Defense>2</Defense>
			<SpDefense>2</SpDefense>
		</Level>
		<!--Level 4-->
		<Level>
			<RequiredExp>37</RequiredExp>
			<HP>2</HP>
			<Attack>2</Attack>
			<SpAttack>2</SpAttack>
			<Defense>2</Defense>
			<SpDefense>2</SpDefense>
		</Level>
		<!--Level 5-->
		<Level>
			<RequiredExp>81</RequiredExp>
			<HP>2</HP>
			<Attack>2</Attack>
			<SpAttack>2</SpAttack>
			<Defense>2</Defense>
			<SpDefense>2</SpDefense>
		</Level>
		<!--Level 6-->
		<Level>
			<RequiredExp>177</RequiredExp>
			<HP>2</HP>
			<Attack>2</Attack>
			<SpAttack>2</SpAttack>
			<Defense>2</Defense>
			<SpDefense>2</SpDefense>
		</Level>
		<!--Level 7-->
		<Level>
			<RequiredExp>274</RequiredExp>
			<HP>2</HP>
			<Attack>2</Attack>
			<SpAttack>2</SpAttack>
			<Defense>2</Defense>
			<SpDefense>2</SpDefense>
		</Level>
		<!--Level 8-->
		<Level>
			<RequiredExp>515</RequiredExp>
			<HP>2</HP>
			<Attack>1</Attack>
			<SpAttack>1</SpAttack>
			<Defense>1</Defense>
			<SpDefense>1</SpDefense>
		</Level>
		<!--Level 9-->
		<Level>
			<RequiredExp>1038</RequiredExp>
			<HP>2</HP>
			<Attack>1</Attack>
			<SpAttack>1</SpAttack>
			<Defense>0</Defense>
			<SpDefense>0</SpDefense>
		</Level>
		<!--Level 10-->
		<Level>
			<RequiredExp>1565</RequiredExp>
			<HP>2</HP>
			<Attack>1</Attack>
			<SpAttack>1</SpAttack>
			<Defense>1</Defense>
			<SpDefense>1</SpDefense>
		</Level>
		<!--Level 11-->
		<Level>
			<RequiredExp>2392</RequiredExp>
			<HP>2</HP>
			<Attack>0</Attack>
			<SpAttack>0</SpAttack>
			<Defense>1</Defense>
			<SpDefense>1</SpDefense>
		</Level>
		<!--Level 12-->
		<Level>
			<RequiredExp>4415</RequiredExp>
			<HP>2</HP>
			<Attack>1</Attack>
			<SpAttack>1</SpAttack>
			<Defense>1</Defense>
			<SpDefense>1</SpDefense>
		</Level>
		<!--Level 13-->
		<Level>
			<RequiredExp>6442</RequiredExp>
			<HP>2</HP>
			<Attack>1</Attack>
			<SpAttack>1</SpAttack>
			<Defense>1</Defense>
			<SpDefense>1</SpDefense>
		</Level>
		<!--Level 14-->
		<Level>
			<RequiredExp>10044</RequiredExp>
			<HP>2</HP>
			<Attack>1</Attack>
			<SpAttack>1</SpAttack>
			<Defense>1</Defense>
			<SpDefense>1</SpDefense>
		</Level>
		<!--Level 15-->
		<Level>
			<RequiredExp>13648</RequiredExp>
			<HP>3</HP>
			<Attack>1</Attack>
			<SpAttack>1</SpAttack>
			<Defense>1</Defense>
			<SpDefense>1</SpDefense>
		</Level>
		<!--Level 16-->
		<Level>
			<RequiredExp>17690</RequiredExp>
			<HP>3</HP>
			<Attack>1</Attack>
			<SpAttack>1</SpAttack>
			<Defense>1</Defense>
			<SpDefense>1</SpDefense>
		</Level>
		<!--Level 17-->
		<Level>
			<RequiredExp>21737</RequiredExp>
			<HP>3</HP>
			<Attack>1</Attack>
			<SpAttack>1</SpAttack>
			<Defense>1</Defense>
			<SpDefense>1</SpDefense>
		</Level>
		<!--Level 18-->
		<Level>
			<RequiredExp>26230</RequiredExp>
			<HP>3</HP>
			<Attack>1</Attack>
			<SpAttack>1</SpAttack>
			<Defense>1</Defense>
			<SpDefense>1</SpDefense>
		</Level>
		<!--Level 19-->
		<Level>
			<RequiredExp>30728</RequiredExp>
			<HP>3</HP>
			<Attack>1</Attack>
			<SpAttack>1</SpAttack>
			<Defense>1</Defense>
			<SpDefense>1</SpDefense>
		</Level>
		<!--Level 20-->
		<Level>
			<RequiredExp>35228</RequiredExp>
			<HP>3</HP>
			<Attack>1</Attack>
			<SpAttack>1</SpAttack>
			<Defense>1</Defense>
			<SpDefense>1</SpDefense>
		</Level>
		<!--Level 21-->
		<Level>
			<RequiredExp>39762</RequiredExp>
			<HP>3</HP>
			<Attack>1</Attack>
			<SpAttack>1</SpAttack>
			<Defense>1</Defense>
			<SpDefense>1</SpDefense>
		</Level>
		<!--Level 22-->
		<Level>
			<RequiredExp>45015</RequiredExp>
			<HP>3</HP>
			<Attack>1</Attack>
			<SpAttack>1</SpAttack>
			<Defense>1</Defense>
			<SpDefense>1</SpDefense>
		</Level>
		<!--Level 23-->
		<Level>
			<RequiredExp>50272</RequiredExp>
			<HP>3</HP>
			<Attack>1</Attack>
			<SpAttack>1</SpAttack>
			<Defense>1</Defense>
			<SpDefense>1</SpDefense>
		</Level>
		<!--Level 24-->
		<Level>
			<RequiredExp>55535</RequiredExp>
			<HP>3</HP>
			<Attack>1</Attack>
			<SpAttack>1</SpAttack>
			<Defense>1</Defense>
			<SpDefense>1</SpDefense>
		</Level>
		<!--Level 25-->
		<Level>
			<RequiredExp>62236</RequiredExp>
			<HP>2</HP>
			<Attack>1</Attack>
			<SpAttack>1</SpAttack>
			<Defense>1</Defense>
			<SpDefense>1</SpDefense>
		</Level>
		<!--Level 26-->
		<Level>
			<RequiredExp>70389</RequiredExp>
			<HP>1</HP>
			<Attack>1</Attack>
			<SpAttack>1</SpAttack>
			<Defense>1</Defense>
			<SpDefense>1</SpDefense>
		</Level>
		<!--Level 27-->
		<Level>
			<RequiredExp>79261</RequiredExp>
			<HP>1</HP>
			<Attack>1</Attack>
			<SpAttack>1</SpAttack>
			<Defense>1</Defense>
			<SpDefense>1</SpDefense>
		</Level>
		<!--Level 28-->
		<Level>
			<RequiredExp>88850</RequiredExp>
			<HP>1</HP>
			<Attack>1</Attack>
			<SpAttack>1</SpAttack>
			<Defense>1</Defense>
			<SpDefense>1</SpDefense>
		</Level>
		<!--Level 29-->
		<Level>
			<RequiredExp>99159</RequiredExp>
			<HP>1</HP>
			<Attack>1</Attack>
			<SpAttack>1</SpAttack>
			<Defense>1</Defense>
			<SpDefense>1</SpDefense>
		</Level>
		<!--Level 30-->
		<Level>
			<RequiredExp>110186</RequiredExp>
			<HP>1</HP>
			<Attack>1</Attack>
			<SpAttack>1</SpAttack>
			<Defense>1</Defense>
			<SpDefense>1</SpDefense>
		</Level>
		<!--Level 31-->
		<Level>
			<RequiredExp>121933</RequiredExp>
			<HP>1</HP>
			<Attack>1</Attack>
			<SpAttack>1</SpAttack>
			<Defense>1</Defense>
			<SpDefense>1</SpDefense>
		</Level>
		<!--Level 32-->
		<Level>
			<RequiredExp>134397</RequiredExp>
			<HP>1</HP>
			<Attack>1</Attack>
			<SpAttack>1</SpAttack>
			<Defense>1</Defense>
			<SpDefense>1</SpDefense>
		</Level>
		<!--Level 33-->
		<Level>
			<RequiredExp>149029</RequiredExp>
			<HP>1</HP>
			<Attack>1</Attack>
			<SpAttack>1</SpAttack>
			<Defense>1</Defense>
			<SpDefense>1</SpDefense>
		</Level>
		<!--Level 34-->
		<Level>
			<RequiredExp>164379</RequiredExp>
			<HP>1</HP>
			<Attack>1</Attack>
			<SpAttack>1</SpAttack>
			<Defense>1</Defense>
			<SpDefense>1</SpDefense>
		</Level>
		<!--Level 35-->
		<Level>
			<RequiredExp>180448</RequiredExp>
			<HP>1</HP>
			<Attack>1</Attack>
			<SpAttack>1</SpAttack>
			<Defense>1</Defense>
			<SpDefense>1</SpDefense>
		</Level>
		<!--Level 36-->
		<Level>
			<RequiredExp>197235</RequiredExp>
			<HP>1</HP>
			<Attack>1</Attack>
			<SpAttack>1</SpAttack>
			<Defense>1</Defense>
			<SpDefense>1</SpDefense>
		</Level>
		<!--Level 37-->
		<Level>
			<RequiredExp>214741</RequiredExp>
			<HP>1</HP>
			<Attack>1</Attack>
			<SpAttack>1</SpAttack>
			<Defense>1</Defense>
			<SpDefense>1</SpDefense>
		</Level>
		<!--Level 38-->
		<Level>
			<RequiredExp>232965</RequiredExp>
			<HP>1</HP>
			<Attack>1</Attack>
			<SpAttack>1</SpAttack>
			<Defense>1</Defense>
			<SpDefense>1</SpDefense>
		</Level>
		<!--Level 39-->
		<Level>
			<RequiredExp>251909</RequiredExp>
			<HP>1</HP>
			<Attack>1</Attack>
			<SpAttack>1</SpAttack>
			<Defense>1</Defense>
			<SpDefense>1</SpDefense>
		</Level>
		<!--Level 40-->
		<Level>
			<RequiredExp>271571</RequiredExp>
			<HP>1</HP>
			<Attack>1</Attack>
			<SpAttack>1</SpAttack>
			<Defense>1</Defense>
			<SpDefense>1</SpDefense>
		</Level>
		<!--Level 41-->
		<Level>
			<RequiredExp>291952</RequiredExp>
			<HP>1</HP>
			<Attack>1</Attack>
			<SpAttack>0</SpAttack>
			<Defense>1</Defense>
			<SpDefense>0</SpDefense>
		</Level>
		<!--Level 42-->
		<Level>
			<RequiredExp>313051</RequiredExp>
			<HP>1</HP>
			<Attack>0</Attack>
			<SpAttack>0</SpAttack>
			<Defense>0</Defense>
			<SpDefense>1</SpDefense>
		</Level>
		<!--Level 43-->
		<Level>
			<RequiredExp>334869</RequiredExp>
			<HP>1</HP>
			<Attack>1</Attack>
			<SpAttack>1</SpAttack>
			<Defense>0</Defense>
			<SpDefense>0</SpDefense>
		</Level>
		<!--Level 44-->
		<Level>
			<RequiredExp>358124</RequiredExp>
			<HP>1</HP>
			<Attack>0</Attack>
			<SpAttack>0</SpAttack>
			<Defense>1</Defense>
			<SpDefense>0</SpDefense>
		</Level>
		<!--Level 45-->
		<Level>
			<RequiredExp>382817</RequiredExp>
			<HP>1</HP>
			<Attack>1</Attack>
			<SpAttack>0</SpAttack>
			<Defense>0</Defense>
			<SpDefense>1</SpDefense>
		</Level>
		<!--Level 46-->
		<Level>
			<RequiredExp>408946</RequiredExp>
			<HP>1</HP>
			<Attack>0</Attack>
			<SpAttack>1</SpAttack>
			<Defense>0</Defense>
			<SpDefense>0</SpDefense>
		</Level>
		<!--Level 47-->
		<Level>
			<RequiredExp>436513</RequiredExp>
			<HP>1</HP>
			<Attack>1</Attack>
			<SpAttack>0</SpAttack>
			<Defense>1</Defense>
			<SpDefense>0</SpDefense>
		</Level>
		<!--Level 48-->
		<Level>
			<RequiredExp>465517</RequiredExp>
			<HP>1</HP>
			<Attack>0</Attack>
			<SpAttack>0</SpAttack>
			<Defense>0</Defense>
			<SpDefense>1</SpDefense>
		</Level>
		<!--Level 49-->
		<Level>
			<RequiredExp>495960</RequiredExp>
			<HP>1</HP>
			<Attack>1</Attack>
			<SpAttack>1</SpAttack>
			<Defense>0</Defense>
			<SpDefense>0</SpDefense>
		</Level>
		<!--Level 50-->
		<Level>
			<RequiredExp>527838</RequiredExp>
			<HP>1</HP>
			<Attack>0</Attack>
			<SpAttack>0</SpAttack>
			<Defense>1</Defense>
			<SpDefense>0</SpDefense>
		</Level>
		<!--Level 51-->
		<Level>
			<RequiredExp>561154</RequiredExp>
			<HP>1</HP>
			<Attack>1</Attack>
			<SpAttack>0</SpAttack>
			<Defense>0</Defense>
			<SpDefense>1</SpDefense>
		</Level>
		<!--Level 52-->
		<Level>
			<RequiredExp>595908</RequiredExp>
			<HP>1</HP>
			<Attack>0</Attack>
			<SpAttack>1</SpAttack>
			<Defense>0</Defense>
			<SpDefense>0</SpDefense>
		</Level>
		<!--Level 53-->
		<Level>
			<RequiredExp>631848</RequiredExp>
			<HP>0</HP>
			<Attack>1</Attack>
			<SpAttack>0</SpAttack>
			<Defense>1</Defense>
			<SpDefense>0</SpDefense>
		</Level>
		<!--Level 54-->
		<Level>
			<RequiredExp>667794</RequiredExp>
			<HP>1</HP>
			<Attack>0</Attack>
			<SpAttack>0</SpAttack>
			<Defense>0</Defense>
			<SpDefense>1</SpDefense>
		</Level>
		<!--Level 55-->
		<Level>
			<RequiredExp>703748</RequiredExp>
			<HP>0</HP>
			<Attack>1</Attack>
			<SpAttack>1</SpAttack>
			<Defense>0</Defense>
			<SpDefense>0</SpDefense>
		</Level>
		<!--Level 56-->
		<Level>
			<RequiredExp>739709</RequiredExp>
			<HP>1</HP>
			<Attack>0</Attack>
			<SpAttack>0</SpAttack>
			<Defense>1</Defense>
			<SpDefense>0</SpDefense>
		</Level>
		<!--Level 57-->
		<Level>
			<RequiredExp>775678</RequiredExp>
			<HP>0</HP>
			<Attack>1</Attack>
			<SpAttack>0</SpAttack>
			<Defense>0</Defense>
			<SpDefense>1</SpDefense>
		</Level>
		<!--Level 58-->
		<Level>
			<RequiredExp>811653</RequiredExp>
			<HP>1</HP>
			<Attack>0</Attack>
			<SpAttack>1</SpAttack>
			<Defense>0</Defense>
			<SpDefense>0</SpDefense>
		</Level>
		<!--Level 59-->
		<Level>
			<RequiredExp>847636</RequiredExp>
			<HP>0</HP>
			<Attack>1</Attack>
			<SpAttack>0</SpAttack>
			<Defense>1</Defense>
			<SpDefense>0</SpDefense>
		</Level>
		<!--Level 60-->
		<Level>
			<RequiredExp>883626</RequiredExp>
			<HP>1</HP>
			<Attack>1</Attack>
			<SpAttack>1</SpAttack>
			<Defense>1</Defense>
			<SpDefense>1</SpDefense>
		</Level>
		<!--Level 61-->
		<Level>
			<RequiredExp>919623</RequiredExp>
			<HP>1</HP>
			<Attack>1</Attack>
			<SpAttack>1</SpAttack>
			<Defense>1</Defense>
			<SpDefense>1</SpDefense>
		</Level>
		<!--Level 62-->
		<Level>
			<RequiredExp>955627</RequiredExp>
			<HP>1</HP>
			<Attack>1</Attack>
			<SpAttack>1</SpAttack>
			<Defense>1</Defense>
			<SpDefense>1</SpDefense>
		</Level>
		<!--Level 63-->
		<Level>
			<RequiredExp>991638</RequiredExp>
			<HP>1</HP>
			<Attack>1</Attack>
			<SpAttack>1</SpAttack>
			<Defense>1</Defense>
			<SpDefense>1</SpDefense>
		</Level>
		<!--Level 64-->
		<Level>
			<RequiredExp>1027657</RequiredExp>
			<HP>1</HP>
			<Attack>1</Attack>
			<SpAttack>1</SpAttack>
			<Defense>1</Defense>
			<SpDefense>1</SpDefense>
		</Level>
		<!--Level 65-->
		<Level>
			<RequiredExp>1063683</RequiredExp>
			<HP>1</HP>
			<Attack>1</Attack>
			<SpAttack>1</SpAttack>
			<Defense>1</Defense>
			<SpDefense>1</SpDefense>
		</Level>
		<!--Level 66-->
		<Level>
			<RequiredExp>1099716</RequiredExp>
			<HP>1</HP>
			<Attack>1</Attack>
			<SpAttack>1</SpAttack>
			<Defense>1</Defense>
			<SpDefense>1</SpDefense>
		</Level>
		<!--Level 67-->
		<Level>
			<RequiredExp>1135756</RequiredExp>
			<HP>1</HP>
			<Attack>1</Attack>
			<SpAttack>1</SpAttack>
			<Defense>1</Defense>
			<SpDefense>1</SpDefense>
		</Level>
		<!--Level 68-->
		<Level>
			<RequiredExp>1171803</RequiredExp>
			<HP>1</HP>
			<Attack>1</Attack>
			<SpAttack>1</SpAttack>
			<Defense>1</Defense>
			<SpDefense>1</SpDefense>
		</Level>
		<!--Level 69-->
		<Level>
			<RequiredExp>1207857</RequiredExp>
			<HP>1</HP>
			<Attack>1</Attack>
			<SpAttack>1</SpAttack>
			<Defense>1</Defense>
			<SpDefense>1</SpDefense>
		</Level>
		<!--Level 70-->
		<Level>
			<RequiredExp>1243919</RequiredExp>
			<HP>1</HP>
			<Attack>1</Attack>
			<SpAttack>1</SpAttack>
			<Defense>1</Defense>
			<SpDefense>1</SpDefense>
		</Level>
		<!--Level 71-->
		<Level>
			<RequiredExp>1279988</RequiredExp>
			<HP>1</HP>
			<Attack>1</Attack>
			<SpAttack>1</SpAttack>
			<Defense>1</Defense>
			<SpDefense>1</SpDefense>
		</Level>
		<!--Level 72-->
		<Level>
			<RequiredExp>1316064</RequiredExp>
			<HP>1</HP>
			<Attack>1</Attack>
			<SpAttack>1</SpAttack>
			<Defense>1</Defense>
			<SpDefense>1</SpDefense>
		</Level>
		<!--Level 73-->
		<Level>
			<RequiredExp>1352148</RequiredExp>
			<HP>1</HP>
			<Attack>1</Attack>
			<SpAttack>1</SpAttack>
			<Defense>1</Defense>
			<SpDefense>1</SpDefense>
		</Level>
		<!--Level 74-->
		<Level>
			<RequiredExp>1388238</RequiredExp>
			<HP>1</HP>
			<Attack>1</Attack>
			<SpAttack>1</SpAttack>
			<Defense>1</Defense>
			<SpDefense>1</SpDefense>
		</Level>
		<!--Level 75-->
		<Level>
			<RequiredExp>1424336</RequiredExp>
			<HP>1</HP>
			<Attack>1</Attack>
			<SpAttack>1</SpAttack>
			<Defense>1</Defense>
			<SpDefense>1</SpDefense>
		</Level>
		<!--Level 76-->
		<Level>
			<RequiredExp>1460440</RequiredExp>
			<HP>1</HP>
			<Attack>1</Attack>
			<SpAttack>1</SpAttack>
			<Defense>1</Defense>
			<SpDefense>1</SpDefense>
		</Level>
		<!--Level 77-->
		<Level>
			<RequiredExp>1496552</RequiredExp>
			<HP>1</HP>
			<Attack>1</Attack>
			<SpAttack>1</SpAttack>
			<Defense>1</Defense>
			<SpDefense>1</SpDefense>
		</Level>
		<!--Level 78-->
		<Level>
			<RequiredExp>1532672</RequiredExp>
			<HP>1</HP>
			<Attack>1</Attack>
			<SpAttack>1</SpAttack>
			<Defense>1</Defense>
			<SpDefense>1</SpDefense>
		</Level>
		<!--Level 79-->
		<Level>
			<RequiredExp>1568798</RequiredExp>
			<HP>1</HP>
			<Attack>1</Attack>
			<SpAttack>1</SpAttack>
			<Defense>1</Defense>
			<SpDefense>1</SpDefense>
		</Level>
		<!--Level 80-->
		<Level>
			<RequiredExp>1604932</RequiredExp>
			<HP>1</HP>
			<Attack>1</Attack>
			<SpAttack>1</SpAttack>
			<Defense>1</Defense>
			<SpDefense>1</SpDefense>
		</Level>
		<!--Level 81-->
		<Level>
			<RequiredExp>1641073</RequiredExp>
			<HP>1</HP>
			<Attack>1</Attack>
			<SpAttack>1</SpAttack>
			<Defense>1</Defense>
			<SpDefense>1</SpDefense>
		</Level>
		<!--Level 82-->
		<Level>
			<RequiredExp>1677220</RequiredExp>
			<HP>1</HP>
			<Attack>1</Attack>
			<SpAttack>1</SpAttack>
			<Defense>1</Defense>
			<SpDefense>1</SpDefense>
		</Level>
		<!--Level 83-->
		<Level>
			<RequiredExp>1713375</RequiredExp>
			<HP>1</HP>
			<Attack>1</Attack>
			<SpAttack>1</SpAttack>
			<Defense>1</Defense>
			<SpDefense>1</SpDefense>
		</Level>
		<!--Level 84-->
		<Level>
			<RequiredExp>1749538</RequiredExp>
			<HP>1</HP>
			<Attack>1</Attack>
			<SpAttack>1</SpAttack>
			<Defense>1</Defense>
			<SpDefense>1</SpDefense>
		</Level>
		<!--Level 85-->
		<Level>
			<RequiredExp>1785708</RequiredExp>
			<HP>1</HP>
			<Attack>1</Attack>
			<SpAttack>1</SpAttack>
			<Defense>1</Defense>
			<SpDefense>1</SpDefense>
		</Level>
		<!--Level 86-->
		<Level>
			<RequiredExp>1821884</RequiredExp>
			<HP>1</HP>
			<Attack>1</Attack>
			<SpAttack>1</SpAttack>
			<Defense>1</Defense>
			<SpDefense>1</SpDefense>
		</Level>
		<!--Level 87-->
		<Level>
			<RequiredExp>1858068</RequiredExp>
			<HP>1</HP>
			<Attack>1</Attack>
			<SpAttack>1</SpAttack>
			<Defense>1</Defense>
			<SpDefense>1</SpDefense>
		</Level>
		<!--Level 88-->
		<Level>
			<RequiredExp>1894259</RequiredExp>
			<HP>1</HP>
			<Attack>1</Attack>
			<SpAttack>1</SpAttack>
			<Defense>1</Defense>
			<SpDefense>1</SpDefense>
		</Level>
		<!--Level 89-->
		<Level>
			<RequiredExp>1930457</RequiredExp>
			<HP>1</HP>
			<Attack>1</Attack>
			<SpAttack>1</SpAttack>
			<Defense>1</Defense>
			<SpDefense>1</SpDefense>
		</Level>
		<!--Level 90-->
		<Level>
			<RequiredExp>1966663</RequiredExp>
			<HP>1</HP>
			<Attack>1</Attack>
			<SpAttack>1</SpAttack>
			<Defense>1</Defense>
			<SpDefense>1</SpDefense>
		</Level>
		<!--Level 91-->
		<Level>
			<RequiredExp>2002875</RequiredExp>
			<HP>1</HP>
			<Attack>1</Attack>
			<SpAttack>1</SpAttack>
			<Defense>1</Defense>
			<SpDefense>1</SpDefense>
		</Level>
		<!--Level 92-->
		<Level>
			<RequiredExp>2039096</RequiredExp>
			<HP>1</HP>
			<Attack>1</Attack>
			<SpAttack>1</SpAttack>
			<Defense>1</Defense>
			<SpDefense>1</SpDefense>
		</Level>
		<!--Level 93-->
		<Level>
			<RequiredExp>2075322</RequiredExp>
			<HP>1</HP>
			<Attack>1</Attack>
			<SpAttack>1</SpAttack>
			<Defense>1</Defense>
			<SpDefense>1</SpDefense>
		</Level>
		<!--Level 94-->
		<Level>
			<RequiredExp>2111556</RequiredExp>
			<HP>1</HP>
			<Attack>1</Attack>
			<SpAttack>1</SpAttack>
			<Defense>1</Defense>
			<SpDefense>1</SpDefense>
		</Level>
		<!--Level 95-->
		<Level>
			<RequiredExp>2147798</RequiredExp>
			<HP>1</HP>
			<Attack>1</Attack>
			<SpAttack>1</SpAttack>
			<Defense>1</Defense>
			<SpDefense>1</SpDefense>
		</Level>
		<!--Level 96-->
		<Level>
			<RequiredExp>2184046</RequiredExp>
			<HP>1</HP>
			<Attack>1</Attack>
			<SpAttack>1</SpAttack>
			<Defense>1</Defense>
			<SpDefense>1</SpDefense>
		</Level>
		<!--Level 97-->
		<Level>
			<RequiredExp>2220302</RequiredExp>
			<HP>1</HP>
			<Attack>1</Attack>
			<SpAttack>1</SpAttack>
			<Defense>1</Defense>
			<SpDefense>1</SpDefense>
		</Level>
		<!--Level 98-->
		<Level>
			<RequiredExp>2256565</RequiredExp>
			<HP>1</HP>
			<Attack>1</Attack>
			<SpAttack>1</SpAttack>
			<Defense>1</Defense>
			<SpDefense>1</SpDefense>
		</Level>
		<!--Level 99-->
		<Level>
			<RequiredExp>2292836</RequiredExp>
			<HP>1</HP>
			<Attack>1</Attack>
			<SpAttack>1</SpAttack>
			<Defense>1</Defense>
			<SpDefense>1</SpDefense>
		</Level>
		<!--Level 100-->
		<Level>
			<RequiredExp>2329155</RequiredExp>
			<HP>1</HP>
			<Attack>1</Attack>
			<SpAttack>1</SpAttack>
			<Defense>1</Defense>
			<SpDefense>1</SpDefense>
		</Level>
	</StatsGrowth>
</Pokemon>
