<?xml version="1.0"?>
<Pokemon gameVersion="EoS">
	<!--In-game text-->
	<Strings>
		<English>
			<Name>Pinsir</Name>
			<Category>Stag Beetle</Category>
		</English>
	</Strings>
	<!--Primary gender entity-->
	<GenderedEntity>
		<PokeID>127</PokeID>
		<Unk31>80</Unk31>
		<PokedexNumber>127</PokedexNumber>
		<Unk1>1</Unk1>
		<EvolutionReq>
			<PreEvoIndex>0</PreEvoIndex>
			<Method>0</Method>
			<Param1>0</Param1>
			<Param2>0</Param2>
		</EvolutionReq>
		<SpriteIndex>137</SpriteIndex>
		<Gender>1</Gender>
		<BodySize>1</BodySize>
		<PrimaryType>12</PrimaryType>
		<SecondaryType>0</SecondaryType>
		<MovementType>0</MovementType>
		<IQGroup>2</IQGroup>
		<PrimaryAbility>9</PrimaryAbility>
		<SecondaryAbility>83</SecondaryAbility>
		<Bitfield>0x30</Bitfield>
		<ExpYield>67</ExpYield>
		<RecruitRate1>82</RecruitRate1>
		<RecruitRate2>164</RecruitRate2>
		<BaseStats>
			<HP>22</HP>
			<Attack>20</Attack>
			<SpAttack>16</SpAttack>
			<Defense>5</Defense>
			<SpDefense>7</SpDefense>
		</BaseStats>
		<Weight>256</Weight>
		<Size>42</Size>
		<Unk17>0xa</Unk17>
		<Unk18>0xa</Unk18>
		<Unk19>0x1</Unk19>
		<Unk20>0x14</Unk20>
		<Unk21>0x64</Unk21>
		<BasePokemonIndex>127</BasePokemonIndex>
		<ExclusiveItems>
			<ItemID>0</ItemID>
			<ItemID>0</ItemID>
			<ItemID>0</ItemID>
			<ItemID>1113</ItemID>
		</ExclusiveItems>
		<Unk27>0x320</Unk27>
		<Unk28>0xf</Unk28>
		<Unk29>0x1e</Unk29>
		<Unk30>0xa</Unk30>
	</GenderedEntity>
	<!--Secondary gender entity-->
	<GenderedEntity>
		<PokeID>127</PokeID>
		<Unk31>80</Unk31>
		<PokedexNumber>127</PokedexNumber>
		<Unk1>1</Unk1>
		<EvolutionReq>
			<PreEvoIndex>0</PreEvoIndex>
			<Method>0</Method>
			<Param1>0</Param1>
			<Param2>0</Param2>
		</EvolutionReq>
		<SpriteIndex>137</SpriteIndex>
		<Gender>2</Gender>
		<BodySize>1</BodySize>
		<PrimaryType>12</PrimaryType>
		<SecondaryType>0</SecondaryType>
		<MovementType>0</MovementType>
		<IQGroup>2</IQGroup>
		<PrimaryAbility>9</PrimaryAbility>
		<SecondaryAbility>83</SecondaryAbility>
		<Bitfield>0x30</Bitfield>
		<ExpYield>67</ExpYield>
		<RecruitRate1>82</RecruitRate1>
		<RecruitRate2>164</RecruitRate2>
		<BaseStats>
			<HP>22</HP>
			<Attack>20</Attack>
			<SpAttack>16</SpAttack>
			<Defense>5</Defense>
			<SpDefense>7</SpDefense>
		</BaseStats>
		<Weight>256</Weight>
		<Size>42</Size>
		<Unk17>0xa</Unk17>
		<Unk18>0xa</Unk18>
		<Unk19>0x1</Unk19>
		<Unk20>0x14</Unk20>
		<Unk21>0x64</Unk21>
		<BasePokemonIndex>127</BasePokemonIndex>
		<ExclusiveItems>
			<ItemID>0</ItemID>
			<ItemID>0</ItemID>
			<ItemID>0</ItemID>
			<ItemID>1113</ItemID>
		</ExclusiveItems>
		<Unk27>0x320</Unk27>
		<Unk28>0xf</Unk28>
		<Unk29>0x1e</Unk29>
		<Unk30>0xa</Unk30>
	</GenderedEntity>
	<!--Moveset from waza_p.bin-->
	<Moveset>
		<!--Learns 14 move(s)-->
		<LevelUpMoves>
			<Learn>
				<Level>1</Level>
				<MoveID>74</MoveID>
			</Learn>
			<Learn>
				<Level>1</Level>
				<MoveID>248</MoveID>
			</Learn>
			<Learn>
				<Level>4</Level>
				<MoveID>125</MoveID>
			</Learn>
			<Learn>
				<Level>8</Level>
				<MoveID>170</MoveID>
			</Learn>
			<Learn>
				<Level>13</Level>
				<MoveID>58</MoveID>
			</Learn>
			<Learn>
				<Level>18</Level>
				<MoveID>340</MoveID>
			</Learn>
			<Learn>
				<Level>21</Level>
				<MoveID>72</MoveID>
			</Learn>
			<Learn>
				<Level>25</Level>
				<MoveID>7</MoveID>
			</Learn>
			<Learn>
				<Level>30</Level>
				<MoveID>470</MoveID>
			</Learn>
			<Learn>
				<Level>35</Level>
				<MoveID>9</MoveID>
			</Learn>
			<Learn>
				<Level>38</Level>
				<MoveID>181</MoveID>
			</Learn>
			<Learn>
				<Level>42</Level>
				<MoveID>116</MoveID>
			</Learn>
			<Learn>
				<Level>47</Level>
				<MoveID>247</MoveID>
			</Learn>
			<Learn>
				<Level>52</Level>
				<MoveID>243</MoveID>
			</Learn>
		</LevelUpMoves>
		<!--Has 7 egg move(s)-->
		<EggMoves>
			<MoveID>121</MoveID>
			<MoveID>167</MoveID>
			<MoveID>190</MoveID>
			<MoveID>311</MoveID>
			<MoveID>314</MoveID>
			<MoveID>440</MoveID>
			<MoveID>516</MoveID>
		</EggMoves>
		<!--Can learn 41 HM/TM move(s)-->
		<HmTmMoves>
			<MoveID>8</MoveID>
			<MoveID>12</MoveID>
			<MoveID>18</MoveID>
			<MoveID>24</MoveID>
			<MoveID>29</MoveID>
			<MoveID>30</MoveID>
			<MoveID>48</MoveID>
			<MoveID>50</MoveID>
			<MoveID>56</MoveID>
			<MoveID>67</MoveID>
			<MoveID>72</MoveID>
			<MoveID>73</MoveID>
			<MoveID>75</MoveID>
			<MoveID>104</MoveID>
			<MoveID>118</MoveID>
			<MoveID>181</MoveID>
			<MoveID>197</MoveID>
			<MoveID>214</MoveID>
			<MoveID>223</MoveID>
			<MoveID>227</MoveID>
			<MoveID>232</MoveID>
			<MoveID>242</MoveID>
			<MoveID>263</MoveID>
			<MoveID>265</MoveID>
			<MoveID>301</MoveID>
			<MoveID>304</MoveID>
			<MoveID>314</MoveID>
			<MoveID>324</MoveID>
			<MoveID>326</MoveID>
			<MoveID>328</MoveID>
			<MoveID>360</MoveID>
			<MoveID>394</MoveID>
			<MoveID>454</MoveID>
			<MoveID>455</MoveID>
			<MoveID>470</MoveID>
			<MoveID>471</MoveID>
			<MoveID>480</MoveID>
			<MoveID>481</MoveID>
			<MoveID>503</MoveID>
			<MoveID>534</MoveID>
			<MoveID>541</MoveID>
		</HmTmMoves>
	</Moveset>
	<!--Moveset from waza_p2.bin-->
	<Moveset>
		<!--Learns 14 move(s)-->
		<LevelUpMoves>
			<Learn>
				<Level>1</Level>
				<MoveID>74</MoveID>
			</Learn>
			<Learn>
				<Level>1</Level>
				<MoveID>248</MoveID>
			</Learn>
			<Learn>
				<Level>4</Level>
				<MoveID>125</MoveID>
			</Learn>
			<Learn>
				<Level>8</Level>
				<MoveID>170</MoveID>
			</Learn>
			<Learn>
				<Level>13</Level>
				<MoveID>58</MoveID>
			</Learn>
			<Learn>
				<Level>18</Level>
				<MoveID>340</MoveID>
			</Learn>
			<Learn>
				<Level>21</Level>
				<MoveID>72</MoveID>
			</Learn>
			<Learn>
				<Level>25</Level>
				<MoveID>7</MoveID>
			</Learn>
			<Learn>
				<Level>30</Level>
				<MoveID>470</MoveID>
			</Learn>
			<Learn>
				<Level>35</Level>
				<MoveID>9</MoveID>
			</Learn>
			<Learn>
				<Level>38</Level>
				<MoveID>181</MoveID>
			</Learn>
			<Learn>
				<Level>42</Level>
				<MoveID>116</MoveID>
			</Learn>
			<Learn>
				<Level>47</Level>
				<MoveID>247</MoveID>
			</Learn>
			<Learn>
				<Level>52</Level>
				<MoveID>243</MoveID>
			</Learn>
		</LevelUpMoves>
		<!--Has 7 egg move(s)-->
		<EggMoves>
			<MoveID>121</MoveID>
			<MoveID>167</MoveID>
			<MoveID>190</MoveID>
			<MoveID>311</MoveID>
			<MoveID>314</MoveID>
			<MoveID>440</MoveID>
			<MoveID>516</MoveID>
		</EggMoves>
		<!--Can learn 41 HM/TM move(s)-->
		<HmTmMoves>
			<MoveID>8</MoveID>
			<MoveID>12</MoveID>
			<MoveID>18</MoveID>
			<MoveID>24</MoveID>
			<MoveID>29</MoveID>
			<MoveID>30</MoveID>
			<MoveID>48</MoveID>
			<MoveID>50</MoveID>
			<MoveID>56</MoveID>
			<MoveID>67</MoveID>
			<MoveID>72</MoveID>
			<MoveID>73</MoveID>
			<MoveID>75</MoveID>
			<MoveID>104</MoveID>
			<MoveID>118</MoveID>
			<MoveID>181</MoveID>
			<MoveID>197</MoveID>
			<MoveID>214</MoveID>
			<MoveID>223</MoveID>
			<MoveID>227</MoveID>
			<MoveID>232</MoveID>
			<MoveID>242</MoveID>
			<MoveID>263</MoveID>
			<MoveID>265</MoveID>
			<MoveID>301</MoveID>
			<MoveID>304</MoveID>
			<MoveID>314</MoveID>
			<MoveID>324</MoveID>
			<MoveID>326</MoveID>
			<MoveID>328</MoveID>
			<MoveID>360</MoveID>
			<MoveID>394</MoveID>
			<MoveID>454</MoveID>
			<MoveID>455</MoveID>
			<MoveID>470</MoveID>
			<MoveID>471</MoveID>
			<MoveID>480</MoveID>
			<MoveID>481</MoveID>
			<MoveID>503</MoveID>
			<MoveID>534</MoveID>
			<MoveID>541</MoveID>
		</HmTmMoves>
	</Moveset>
	<!--Stats growth and exp requirements-->
	<StatsGrowth>
		<!--Level 1-->
		<Level>
			<RequiredExp>0</RequiredExp>
			<HP>0</HP>
			<Attack>0</Attack>
			<SpAttack>0</SpAttack>
			<Defense>0</Defense>
			<SpDefense>0</SpDefense>
		</Level>
		<!--Level 2-->
		<Level>
			<RequiredExp>8</RequiredExp>
			<HP>1</HP>
			<Attack>1</Attack>
			<SpAttack>1</SpAttack>
			<Defense>1</Defense>
			<SpDefense>1</SpDefense>
		</Level>
		<!--Level 3-->
		<Level>
			<RequiredExp>21</RequiredExp>
			<HP>1</HP>
			<Attack>1</Attack>
			<SpAttack>1</SpAttack>
			<Defense>1</Defense>
			<SpDefense>1</SpDefense>
		</Level>
		<!--Level 4-->
		<Level>
			<RequiredExp>37</RequiredExp>
			<HP>1</HP>
			<Attack>1</Attack>
			<SpAttack>0</SpAttack>
			<Defense>1</Defense>
			<SpDefense>0</SpDefense>
		</Level>
		<!--Level 5-->
		<Level>
			<RequiredExp>80</RequiredExp>
			<HP>1</HP>
			<Attack>1</Attack>
			<SpAttack>1</SpAttack>
			<Defense>1</Defense>
			<SpDefense>1</SpDefense>
		</Level>
		<!--Level 6-->
		<Level>
			<RequiredExp>176</RequiredExp>
			<HP>1</HP>
			<Attack>1</Attack>
			<SpAttack>1</SpAttack>
			<Defense>1</Defense>
			<SpDefense>1</SpDefense>
		</Level>
		<!--Level 7-->
		<Level>
			<RequiredExp>273</RequiredExp>
			<HP>1</HP>
			<Attack>1</Attack>
			<SpAttack>0</SpAttack>
			<Defense>1</Defense>
			<SpDefense>0</SpDefense>
		</Level>
		<!--Level 8-->
		<Level>
			<RequiredExp>512</RequiredExp>
			<HP>1</HP>
			<Attack>1</Attack>
			<SpAttack>1</SpAttack>
			<Defense>1</Defense>
			<SpDefense>1</SpDefense>
		</Level>
		<!--Level 9-->
		<Level>
			<RequiredExp>1033</RequiredExp>
			<HP>1</HP>
			<Attack>1</Attack>
			<SpAttack>0</SpAttack>
			<Defense>1</Defense>
			<SpDefense>1</SpDefense>
		</Level>
		<!--Level 10-->
		<Level>
			<RequiredExp>1557</RequiredExp>
			<HP>1</HP>
			<Attack>1</Attack>
			<SpAttack>1</SpAttack>
			<Defense>1</Defense>
			<SpDefense>0</SpDefense>
		</Level>
		<!--Level 11-->
		<Level>
			<RequiredExp>2380</RequiredExp>
			<HP>1</HP>
			<Attack>1</Attack>
			<SpAttack>1</SpAttack>
			<Defense>1</Defense>
			<SpDefense>1</SpDefense>
		</Level>
		<!--Level 12-->
		<Level>
			<RequiredExp>4393</RequiredExp>
			<HP>1</HP>
			<Attack>1</Attack>
			<SpAttack>0</SpAttack>
			<Defense>1</Defense>
			<SpDefense>1</SpDefense>
		</Level>
		<!--Level 13-->
		<Level>
			<RequiredExp>6411</RequiredExp>
			<HP>1</HP>
			<Attack>1</Attack>
			<SpAttack>1</SpAttack>
			<Defense>1</Defense>
			<SpDefense>0</SpDefense>
		</Level>
		<!--Level 14-->
		<Level>
			<RequiredExp>9995</RequiredExp>
			<HP>1</HP>
			<Attack>1</Attack>
			<SpAttack>1</SpAttack>
			<Defense>1</Defense>
			<SpDefense>1</SpDefense>
		</Level>
		<!--Level 15-->
		<Level>
			<RequiredExp>13583</RequiredExp>
			<HP>1</HP>
			<Attack>1</Attack>
			<SpAttack>0</SpAttack>
			<Defense>1</Defense>
			<SpDefense>1</SpDefense>
		</Level>
		<!--Level 16-->
		<Level>
			<RequiredExp>17605</RequiredExp>
			<HP>2</HP>
			<Attack>2</Attack>
			<SpAttack>1</SpAttack>
			<Defense>2</Defense>
			<SpDefense>3</SpDefense>
		</Level>
		<!--Level 17-->
		<Level>
			<RequiredExp>21632</RequiredExp>
			<HP>2</HP>
			<Attack>2</Attack>
			<SpAttack>2</SpAttack>
			<Defense>1</Defense>
			<SpDefense>2</SpDefense>
		</Level>
		<!--Level 18-->
		<Level>
			<RequiredExp>26104</RequiredExp>
			<HP>2</HP>
			<Attack>2</Attack>
			<SpAttack>2</SpAttack>
			<Defense>2</Defense>
			<SpDefense>1</SpDefense>
		</Level>
		<!--Level 19-->
		<Level>
			<RequiredExp>30579</RequiredExp>
			<HP>2</HP>
			<Attack>2</Attack>
			<SpAttack>1</SpAttack>
			<Defense>1</Defense>
			<SpDefense>3</SpDefense>
		</Level>
		<!--Level 20-->
		<Level>
			<RequiredExp>35058</RequiredExp>
			<HP>3</HP>
			<Attack>2</Attack>
			<SpAttack>2</SpAttack>
			<Defense>2</Defense>
			<SpDefense>1</SpDefense>
		</Level>
		<!--Level 21-->
		<Level>
			<RequiredExp>39570</RequiredExp>
			<HP>3</HP>
			<Attack>1</Attack>
			<SpAttack>2</SpAttack>
			<Defense>1</Defense>
			<SpDefense>1</SpDefense>
		</Level>
		<!--Level 22-->
		<Level>
			<RequiredExp>44798</RequiredExp>
			<HP>3</HP>
			<Attack>1</Attack>
			<SpAttack>1</SpAttack>
			<Defense>2</Defense>
			<SpDefense>1</SpDefense>
		</Level>
		<!--Level 23-->
		<Level>
			<RequiredExp>50030</RequiredExp>
			<HP>3</HP>
			<Attack>1</Attack>
			<SpAttack>2</SpAttack>
			<Defense>1</Defense>
			<SpDefense>3</SpDefense>
		</Level>
		<!--Level 24-->
		<Level>
			<RequiredExp>55267</RequiredExp>
			<HP>2</HP>
			<Attack>1</Attack>
			<SpAttack>2</SpAttack>
			<Defense>2</Defense>
			<SpDefense>1</SpDefense>
		</Level>
		<!--Level 25-->
		<Level>
			<RequiredExp>61936</RequiredExp>
			<HP>2</HP>
			<Attack>1</Attack>
			<SpAttack>1</SpAttack>
			<Defense>1</Defense>
			<SpDefense>1</SpDefense>
		</Level>
		<!--Level 26-->
		<Level>
			<RequiredExp>70050</RequiredExp>
			<HP>2</HP>
			<Attack>1</Attack>
			<SpAttack>2</SpAttack>
			<Defense>2</Defense>
			<SpDefense>3</SpDefense>
		</Level>
		<!--Level 27-->
		<Level>
			<RequiredExp>78878</RequiredExp>
			<HP>2</HP>
			<Attack>1</Attack>
			<SpAttack>2</SpAttack>
			<Defense>1</Defense>
			<SpDefense>1</SpDefense>
		</Level>
		<!--Level 28-->
		<Level>
			<RequiredExp>88422</RequiredExp>
			<HP>2</HP>
			<Attack>1</Attack>
			<SpAttack>1</SpAttack>
			<Defense>1</Defense>
			<SpDefense>1</SpDefense>
		</Level>
		<!--Level 29-->
		<Level>
			<RequiredExp>98681</RequiredExp>
			<HP>2</HP>
			<Attack>1</Attack>
			<SpAttack>2</SpAttack>
			<Defense>1</Defense>
			<SpDefense>3</SpDefense>
		</Level>
		<!--Level 30-->
		<Level>
			<RequiredExp>109655</RequiredExp>
			<HP>2</HP>
			<Attack>1</Attack>
			<SpAttack>2</SpAttack>
			<Defense>1</Defense>
			<SpDefense>1</SpDefense>
		</Level>
		<!--Level 31-->
		<Level>
			<RequiredExp>121345</RequiredExp>
			<HP>2</HP>
			<Attack>1</Attack>
			<SpAttack>1</SpAttack>
			<Defense>1</Defense>
			<SpDefense>1</SpDefense>
		</Level>
		<!--Level 32-->
		<Level>
			<RequiredExp>133749</RequiredExp>
			<HP>2</HP>
			<Attack>1</Attack>
			<SpAttack>1</SpAttack>
			<Defense>1</Defense>
			<SpDefense>1</SpDefense>
		</Level>
		<!--Level 33-->
		<Level>
			<RequiredExp>148310</RequiredExp>
			<HP>2</HP>
			<Attack>1</Attack>
			<SpAttack>1</SpAttack>
			<Defense>1</Defense>
			<SpDefense>1</SpDefense>
		</Level>
		<!--Level 34-->
		<Level>
			<RequiredExp>163586</RequiredExp>
			<HP>2</HP>
			<Attack>1</Attack>
			<SpAttack>1</SpAttack>
			<Defense>1</Defense>
			<SpDefense>1</SpDefense>
		</Level>
		<!--Level 35-->
		<Level>
			<RequiredExp>179577</RequiredExp>
			<HP>2</HP>
			<Attack>1</Attack>
			<SpAttack>1</SpAttack>
			<Defense>1</Defense>
			<SpDefense>1</SpDefense>
		</Level>
		<!--Level 36-->
		<Level>
			<RequiredExp>196284</RequiredExp>
			<HP>1</HP>
			<Attack>1</Attack>
			<SpAttack>1</SpAttack>
			<Defense>1</Defense>
			<SpDefense>1</SpDefense>
		</Level>
		<!--Level 37-->
		<Level>
			<RequiredExp>213705</RequiredExp>
			<HP>1</HP>
			<Attack>1</Attack>
			<SpAttack>1</SpAttack>
			<Defense>1</Defense>
			<SpDefense>1</SpDefense>
		</Level>
		<!--Level 38-->
		<Level>
			<RequiredExp>231842</RequiredExp>
			<HP>1</HP>
			<Attack>1</Attack>
			<SpAttack>1</SpAttack>
			<Defense>1</Defense>
			<SpDefense>1</SpDefense>
		</Level>
		<!--Level 39-->
		<Level>
			<RequiredExp>250694</RequiredExp>
			<HP>1</HP>
			<Attack>1</Attack>
			<SpAttack>1</SpAttack>
			<Defense>1</Defense>
			<SpDefense>1</SpDefense>
		</Level>
		<!--Level 40-->
		<Level>
			<RequiredExp>270261</RequiredExp>
			<HP>1</HP>
			<Attack>0</Attack>
			<SpAttack>1</SpAttack>
			<Defense>1</Defense>
			<SpDefense>1</SpDefense>
		</Level>
		<!--Level 41-->
		<Level>
			<RequiredExp>290544</RequiredExp>
			<HP>1</HP>
			<Attack>0</Attack>
			<SpAttack>1</SpAttack>
			<Defense>1</Defense>
			<SpDefense>1</SpDefense>
		</Level>
		<!--Level 42-->
		<Level>
			<RequiredExp>311541</RequiredExp>
			<HP>1</HP>
			<Attack>1</Attack>
			<SpAttack>0</SpAttack>
			<Defense>0</Defense>
			<SpDefense>0</SpDefense>
		</Level>
		<!--Level 43-->
		<Level>
			<RequiredExp>333254</RequiredExp>
			<HP>1</HP>
			<Attack>1</Attack>
			<SpAttack>1</SpAttack>
			<Defense>1</Defense>
			<SpDefense>1</SpDefense>
		</Level>
		<!--Level 44-->
		<Level>
			<RequiredExp>356397</RequiredExp>
			<HP>1</HP>
			<Attack>0</Attack>
			<SpAttack>1</SpAttack>
			<Defense>1</Defense>
			<SpDefense>1</SpDefense>
		</Level>
		<!--Level 45-->
		<Level>
			<RequiredExp>380970</RequiredExp>
			<HP>1</HP>
			<Attack>1</Attack>
			<SpAttack>0</SpAttack>
			<Defense>0</Defense>
			<SpDefense>0</SpDefense>
		</Level>
		<!--Level 46-->
		<Level>
			<RequiredExp>406974</RequiredExp>
			<HP>1</HP>
			<Attack>1</Attack>
			<SpAttack>1</SpAttack>
			<Defense>1</Defense>
			<SpDefense>1</SpDefense>
		</Level>
		<!--Level 47-->
		<Level>
			<RequiredExp>434408</RequiredExp>
			<HP>1</HP>
			<Attack>0</Attack>
			<SpAttack>1</SpAttack>
			<Defense>1</Defense>
			<SpDefense>1</SpDefense>
		</Level>
		<!--Level 48-->
		<Level>
			<RequiredExp>463272</RequiredExp>
			<HP>1</HP>
			<Attack>1</Attack>
			<SpAttack>0</SpAttack>
			<Defense>0</Defense>
			<SpDefense>0</SpDefense>
		</Level>
		<!--Level 49-->
		<Level>
			<RequiredExp>493568</RequiredExp>
			<HP>1</HP>
			<Attack>1</Attack>
			<SpAttack>1</SpAttack>
			<Defense>1</Defense>
			<SpDefense>1</SpDefense>
		</Level>
		<!--Level 50-->
		<Level>
			<RequiredExp>525293</RequiredExp>
			<HP>1</HP>
			<Attack>0</Attack>
			<SpAttack>1</SpAttack>
			<Defense>1</Defense>
			<SpDefense>1</SpDefense>
		</Level>
		<!--Level 51-->
		<Level>
			<RequiredExp>558448</RequiredExp>
			<HP>0</HP>
			<Attack>1</Attack>
			<SpAttack>0</SpAttack>
			<Defense>0</Defense>
			<SpDefense>0</SpDefense>
		</Level>
		<!--Level 52-->
		<Level>
			<RequiredExp>593034</RequiredExp>
			<HP>1</HP>
			<Attack>1</Attack>
			<SpAttack>1</SpAttack>
			<Defense>1</Defense>
			<SpDefense>1</SpDefense>
		</Level>
		<!--Level 53-->
		<Level>
			<RequiredExp>628801</RequiredExp>
			<HP>0</HP>
			<Attack>0</Attack>
			<SpAttack>1</SpAttack>
			<Defense>1</Defense>
			<SpDefense>1</SpDefense>
		</Level>
		<!--Level 54-->
		<Level>
			<RequiredExp>664574</RequiredExp>
			<HP>1</HP>
			<Attack>1</Attack>
			<SpAttack>0</SpAttack>
			<Defense>0</Defense>
			<SpDefense>0</SpDefense>
		</Level>
		<!--Level 55-->
		<Level>
			<RequiredExp>700354</RequiredExp>
			<HP>0</HP>
			<Attack>1</Attack>
			<SpAttack>1</SpAttack>
			<Defense>1</Defense>
			<SpDefense>1</SpDefense>
		</Level>
		<!--Level 56-->
		<Level>
			<RequiredExp>736142</RequiredExp>
			<HP>1</HP>
			<Attack>0</Attack>
			<SpAttack>1</SpAttack>
			<Defense>1</Defense>
			<SpDefense>1</SpDefense>
		</Level>
		<!--Level 57-->
		<Level>
			<RequiredExp>771937</RequiredExp>
			<HP>0</HP>
			<Attack>1</Attack>
			<SpAttack>0</SpAttack>
			<Defense>0</Defense>
			<SpDefense>0</SpDefense>
		</Level>
		<!--Level 58-->
		<Level>
			<RequiredExp>807739</RequiredExp>
			<HP>1</HP>
			<Attack>1</Attack>
			<SpAttack>1</SpAttack>
			<Defense>1</Defense>
			<SpDefense>1</SpDefense>
		</Level>
		<!--Level 59-->
		<Level>
			<RequiredExp>843548</RequiredExp>
			<HP>0</HP>
			<Attack>0</Attack>
			<SpAttack>1</SpAttack>
			<Defense>1</Defense>
			<SpDefense>1</SpDefense>
		</Level>
		<!--Level 60-->
		<Level>
			<RequiredExp>879364</RequiredExp>
			<HP>1</HP>
			<Attack>1</Attack>
			<SpAttack>1</SpAttack>
			<Defense>1</Defense>
			<SpDefense>1</SpDefense>
		</Level>
		<!--Level 61-->
		<Level>
			<RequiredExp>915187</RequiredExp>
			<HP>1</HP>
			<Attack>1</Attack>
			<SpAttack>1</SpAttack>
			<Defense>1</Defense>
			<SpDefense>1</SpDefense>
		</Level>
		<!--Level 62-->
		<Level>
			<RequiredExp>951018</RequiredExp>
			<HP>1</HP>
			<Attack>1</Attack>
			<SpAttack>1</SpAttack>
			<Defense>1</Defense>
			<SpDefense>1</SpDefense>
		</Level>
		<!--Level 63-->
		<Level>
			<RequiredExp>986856</RequiredExp>
			<HP>1</HP>
			<Attack>1</Attack>
			<SpAttack>1</SpAttack>
			<Defense>1</Defense>
			<SpDefense>1</SpDefense>
		</Level>
		<!--Level 64-->
		<Level>
			<RequiredExp>1022701</RequiredExp>
			<HP>1</HP>
			<Attack>1</Attack>
			<SpAttack>1</SpAttack>
			<Defense>1</Defense>
			<SpDefense>1</SpDefense>
		</Level>
		<!--Level 65-->
		<Level>
			<RequiredExp>1058553</RequiredExp>
			<HP>1</HP>
			<Attack>1</Attack>
			<SpAttack>1</SpAttack>
			<Defense>1</Defense>
			<SpDefense>1</SpDefense>
		</Level>
		<!--Level 66-->
		<Level>
			<RequiredExp>1094412</RequiredExp>
			<HP>1</HP>
			<Attack>1</Attack>
			<SpAttack>1</SpAttack>
			<Defense>1</Defense>
			<SpDefense>1</SpDefense>
		</Level>
		<!--Level 67-->
		<Level>
			<RequiredExp>1130279</RequiredExp>
			<HP>1</HP>
			<Attack>1</Attack>
			<SpAttack>1</SpAttack>
			<Defense>1</Defense>
			<SpDefense>1</SpDefense>
		</Level>
		<!--Level 68-->
		<Level>
			<RequiredExp>1166152</RequiredExp>
			<HP>1</HP>
			<Attack>1</Attack>
			<SpAttack>1</SpAttack>
			<Defense>1</Defense>
			<SpDefense>1</SpDefense>
		</Level>
		<!--Level 69-->
		<Level>
			<RequiredExp>1202032</RequiredExp>
			<HP>1</HP>
			<Attack>1</Attack>
			<SpAttack>1</SpAttack>
			<Defense>1</Defense>
			<SpDefense>1</SpDefense>
		</Level>
		<!--Level 70-->
		<Level>
			<RequiredExp>1237920</RequiredExp>
			<HP>1</HP>
			<Attack>1</Attack>
			<SpAttack>1</SpAttack>
			<Defense>1</Defense>
			<SpDefense>1</SpDefense>
		</Level>
		<!--Level 71-->
		<Level>
			<RequiredExp>1273815</RequiredExp>
			<HP>1</HP>
			<Attack>1</Attack>
			<SpAttack>1</SpAttack>
			<Defense>1</Defense>
			<SpDefense>1</SpDefense>
		</Level>
		<!--Level 72-->
		<Level>
			<RequiredExp>1309717</RequiredExp>
			<HP>1</HP>
			<Attack>1</Attack>
			<SpAttack>1</SpAttack>
			<Defense>1</Defense>
			<SpDefense>1</SpDefense>
		</Level>
		<!--Level 73-->
		<Level>
			<RequiredExp>1345626</RequiredExp>
			<HP>1</HP>
			<Attack>1</Attack>
			<SpAttack>1</SpAttack>
			<Defense>1</Defense>
			<SpDefense>1</SpDefense>
		</Level>
		<!--Level 74-->
		<Level>
			<RequiredExp>1381543</RequiredExp>
			<HP>1</HP>
			<Attack>1</Attack>
			<SpAttack>1</SpAttack>
			<Defense>1</Defense>
			<SpDefense>1</SpDefense>
		</Level>
		<!--Level 75-->
		<Level>
			<RequiredExp>1417466</RequiredExp>
			<HP>1</HP>
			<Attack>1</Attack>
			<SpAttack>1</SpAttack>
			<Defense>1</Defense>
			<SpDefense>1</SpDefense>
		</Level>
		<!--Level 76-->
		<Level>
			<RequiredExp>1453397</RequiredExp>
			<HP>1</HP>
			<Attack>1</Attack>
			<SpAttack>1</SpAttack>
			<Defense>1</Defense>
			<SpDefense>1</SpDefense>
		</Level>
		<!--Level 77-->
		<Level>
			<RequiredExp>1489335</RequiredExp>
			<HP>1</HP>
			<Attack>1</Attack>
			<SpAttack>1</SpAttack>
			<Defense>1</Defense>
			<SpDefense>1</SpDefense>
		</Level>
		<!--Level 78-->
		<Level>
			<RequiredExp>1525280</RequiredExp>
			<HP>1</HP>
			<Attack>1</Attack>
			<SpAttack>1</SpAttack>
			<Defense>1</Defense>
			<SpDefense>1</SpDefense>
		</Level>
		<!--Level 79-->
		<Level>
			<RequiredExp>1561232</RequiredExp>
			<HP>1</HP>
			<Attack>1</Attack>
			<SpAttack>1</SpAttack>
			<Defense>1</Defense>
			<SpDefense>1</SpDefense>
		</Level>
		<!--Level 80-->
		<Level>
			<RequiredExp>1597191</RequiredExp>
			<HP>1</HP>
			<Attack>1</Attack>
			<SpAttack>1</SpAttack>
			<Defense>1</Defense>
			<SpDefense>1</SpDefense>
		</Level>
		<!--Level 81-->
		<Level>
			<RequiredExp>1633158</RequiredExp>
			<HP>1</HP>
			<Attack>1</Attack>
			<SpAttack>1</SpAttack>
			<Defense>1</Defense>
			<SpDefense>1</SpDefense>
		</Level>
		<!--Level 82-->
		<Level>
			<RequiredExp>1669131</RequiredExp>
			<HP>1</HP>
			<Attack>1</Attack>
			<SpAttack>1</SpAttack>
			<Defense>1</Defense>
			<SpDefense>1</SpDefense>
		</Level>
		<!--Level 83-->
		<Level>
			<RequiredExp>1705112</RequiredExp>
			<HP>1</HP>
			<Attack>1</Attack>
			<SpAttack>1</SpAttack>
			<Defense>1</Defense>
			<SpDefense>1</SpDefense>
		</Level>
		<!--Level 84-->
		<Level>
			<RequiredExp>1741100</RequiredExp>
			<HP>1</HP>
			<Attack>1</Attack>
			<SpAttack>1</SpAttack>
			<Defense>1</Defense>
			<SpDefense>1</SpDefense>
		</Level>
		<!--Level 85-->
		<Level>
			<RequiredExp>1777096</RequiredExp>
			<HP>1</HP>
			<Attack>1</Attack>
			<SpAttack>1</SpAttack>
			<Defense>1</Defense>
			<SpDefense>1</SpDefense>
		</Level>
		<!--Level 86-->
		<Level>
			<RequiredExp>1813098</RequiredExp>
			<HP>1</HP>
			<Attack>1</Attack>
			<SpAttack>1</SpAttack>
			<Defense>1</Defense>
			<SpDefense>1</SpDefense>
		</Level>
		<!--Level 87-->
		<Level>
			<RequiredExp>1849107</RequiredExp>
			<HP>1</HP>
			<Attack>1</Attack>
			<SpAttack>1</SpAttack>
			<Defense>1</Defense>
			<SpDefense>1</SpDefense>
		</Level>
		<!--Level 88-->
		<Level>
			<RequiredExp>1885124</RequiredExp>
			<HP>1</HP>
			<Attack>1</Attack>
			<SpAttack>1</SpAttack>
			<Defense>1</Defense>
			<SpDefense>1</SpDefense>
		</Level>
		<!--Level 89-->
		<Level>
			<RequiredExp>1921147</RequiredExp>
			<HP>1</HP>
			<Attack>1</Attack>
			<SpAttack>1</SpAttack>
			<Defense>1</Defense>
			<SpDefense>1</SpDefense>
		</Level>
		<!--Level 90-->
		<Level>
			<RequiredExp>1957178</RequiredExp>
			<HP>1</HP>
			<Attack>1</Attack>
			<SpAttack>1</SpAttack>
			<Defense>1</Defense>
			<SpDefense>1</SpDefense>
		</Level>
		<!--Level 91-->
		<Level>
			<RequiredExp>1993216</RequiredExp>
			<HP>1</HP>
			<Attack>1</Attack>
			<SpAttack>1</SpAttack>
			<Defense>1</Defense>
			<SpDefense>1</SpDefense>
		</Level>
		<!--Level 92-->
		<Level>
			<RequiredExp>2029261</RequiredExp>
			<HP>1</HP>
			<Attack>1</Attack>
			<SpAttack>1</SpAttack>
			<Defense>1</Defense>
			<SpDefense>1</SpDefense>
		</Level>
		<!--Level 93-->
		<Level>
			<RequiredExp>2065313</RequiredExp>
			<HP>1</HP>
			<Attack>1</Attack>
			<SpAttack>1</SpAttack>
			<Defense>1</Defense>
			<SpDefense>1</SpDefense>
		</Level>
		<!--Level 94-->
		<Level>
			<RequiredExp>2101373</RequiredExp>
			<HP>1</HP>
			<Attack>1</Attack>
			<SpAttack>1</SpAttack>
			<Defense>1</Defense>
			<SpDefense>1</SpDefense>
		</Level>
		<!--Level 95-->
		<Level>
			<RequiredExp>2137440</RequiredExp>
			<HP>1</HP>
			<Attack>1</Attack>
			<SpAttack>1</SpAttack>
			<Defense>1</Defense>
			<SpDefense>1</SpDefense>
		</Level>
		<!--Level 96-->
		<Level>
			<RequiredExp>2173513</RequiredExp>
			<HP>1</HP>
			<Attack>1</Attack>
			<SpAttack>1</SpAttack>
			<Defense>1</Defense>
			<SpDefense>1</SpDefense>
		</Level>
		<!--Level 97-->
		<Level>
			<RequiredExp>2209594</RequiredExp>
			<HP>1</HP>
			<Attack>1</Attack>
			<SpAttack>1</SpAttack>
			<Defense>1</Defense>
			<SpDefense>1</SpDefense>
		</Level>
		<!--Level 98-->
		<Level>
			<RequiredExp>2245682</RequiredExp>
			<HP>1</HP>
			<Attack>1</Attack>
			<SpAttack>1</SpAttack>
			<Defense>1</Defense>
			<SpDefense>1</SpDefense>
		</Level>
		<!--Level 99-->
		<Level>
			<RequiredExp>2281778</RequiredExp>
			<HP>1</HP>
			<Attack>1</Attack>
			<SpAttack>1</SpAttack>
			<Defense>1</Defense>
			<SpDefense>1</SpDefense>
		</Level>
		<!--Level 100-->
		<Level>
			<RequiredExp>2317922</RequiredExp>
			<HP>1</HP>
			<Attack>1</Attack>
			<SpAttack>1</SpAttack>
			<Defense>1</Defense>
			<SpDefense>1</SpDefense>
		</Level>
	</StatsGrowth>
</Pokemon>
