<?xml version="1.0"?>
<Pokemon gameVersion="EoS">
	<!--In-game text-->
	<Strings>
		<English>
			<Name>Swablu</Name>
			<Category>Cotton Bird</Category>
		</English>
	</Strings>
	<!--Primary gender entity-->
	<GenderedEntity>
		<PokeID>333</PokeID>
		<Unk31>229</Unk31>
		<PokedexNumber>333</PokedexNumber>
		<Unk1>1</Unk1>
		<EvolutionReq>
			<PreEvoIndex>0</PreEvoIndex>
			<Method>0</Method>
			<Param1>0</Param1>
			<Param2>0</Param2>
		</EvolutionReq>
		<SpriteIndex>530</SpriteIndex>
		<Gender>1</Gender>
		<BodySize>1</BodySize>
		<PrimaryType>1</PrimaryType>
		<SecondaryType>10</SecondaryType>
		<MovementType>2</MovementType>
		<IQGroup>7</IQGroup>
		<PrimaryAbility>20</PrimaryAbility>
		<SecondaryAbility>0</SecondaryAbility>
		<Bitfield>0x70</Bitfield>
		<ExpYield>107</ExpYield>
		<RecruitRate1>64</RecruitRate1>
		<RecruitRate2>64</RecruitRate2>
		<BaseStats>
			<HP>44</HP>
			<Attack>13</Attack>
			<SpAttack>15</SpAttack>
			<Defense>11</Defense>
			<SpDefense>12</SpDefense>
		</BaseStats>
		<Weight>153</Weight>
		<Size>26</Size>
		<Unk17>0xa</Unk17>
		<Unk18>0xa</Unk18>
		<Unk19>0x1</Unk19>
		<Unk20>0x8</Unk20>
		<Unk21>0x64</Unk21>
		<BasePokemonIndex>361</BasePokemonIndex>
		<ExclusiveItems>
			<ItemID>0</ItemID>
			<ItemID>0</ItemID>
			<ItemID>0</ItemID>
			<ItemID>1255</ItemID>
		</ExclusiveItems>
		<Unk27>0x320</Unk27>
		<Unk28>0xf</Unk28>
		<Unk29>0x1e</Unk29>
		<Unk30>0xa</Unk30>
	</GenderedEntity>
	<!--Secondary gender entity-->
	<GenderedEntity>
		<PokeID>333</PokeID>
		<Unk31>229</Unk31>
		<PokedexNumber>333</PokedexNumber>
		<Unk1>1</Unk1>
		<EvolutionReq>
			<PreEvoIndex>0</PreEvoIndex>
			<Method>0</Method>
			<Param1>0</Param1>
			<Param2>0</Param2>
		</EvolutionReq>
		<SpriteIndex>530</SpriteIndex>
		<Gender>2</Gender>
		<BodySize>1</BodySize>
		<PrimaryType>1</PrimaryType>
		<SecondaryType>10</SecondaryType>
		<MovementType>2</MovementType>
		<IQGroup>7</IQGroup>
		<PrimaryAbility>20</PrimaryAbility>
		<SecondaryAbility>0</SecondaryAbility>
		<Bitfield>0x70</Bitfield>
		<ExpYield>107</ExpYield>
		<RecruitRate1>64</RecruitRate1>
		<RecruitRate2>64</RecruitRate2>
		<BaseStats>
			<HP>44</HP>
			<Attack>13</Attack>
			<SpAttack>15</SpAttack>
			<Defense>11</Defense>
			<SpDefense>12</SpDefense>
		</BaseStats>
		<Weight>153</Weight>
		<Size>26</Size>
		<Unk17>0xa</Unk17>
		<Unk18>0xa</Unk18>
		<Unk19>0x1</Unk19>
		<Unk20>0x8</Unk20>
		<Unk21>0x64</Unk21>
		<BasePokemonIndex>361</BasePokemonIndex>
		<ExclusiveItems>
			<ItemID>0</ItemID>
			<ItemID>0</ItemID>
			<ItemID>0</ItemID>
			<ItemID>1255</ItemID>
		</ExclusiveItems>
		<Unk27>0x320</Unk27>
		<Unk28>0xf</Unk28>
		<Unk29>0x1e</Unk29>
		<Unk30>0xa</Unk30>
	</GenderedEntity>
	<!--Moveset from waza_p.bin-->
	<Moveset>
		<!--Learns 13 move(s)-->
		<LevelUpMoves>
			<Learn>
				<Level>1</Level>
				<MoveID>174</MoveID>
			</Learn>
			<Learn>
				<Level>1</Level>
				<MoveID>217</MoveID>
			</Learn>
			<Learn>
				<Level>5</Level>
				<MoveID>46</MoveID>
			</Learn>
			<Learn>
				<Level>9</Level>
				<MoveID>34</MoveID>
			</Learn>
			<Learn>
				<Level>13</Level>
				<MoveID>311</MoveID>
			</Learn>
			<Learn>
				<Level>18</Level>
				<MoveID>134</MoveID>
			</Learn>
			<Learn>
				<Level>23</Level>
				<MoveID>130</MoveID>
			</Learn>
			<Learn>
				<Level>28</Level>
				<MoveID>203</MoveID>
			</Learn>
			<Learn>
				<Level>32</Level>
				<MoveID>471</MoveID>
			</Learn>
			<Learn>
				<Level>36</Level>
				<MoveID>40</MoveID>
			</Learn>
			<Learn>
				<Level>40</Level>
				<MoveID>339</MoveID>
			</Learn>
			<Learn>
				<Level>45</Level>
				<MoveID>539</MoveID>
			</Learn>
			<Learn>
				<Level>50</Level>
				<MoveID>293</MoveID>
			</Learn>
		</LevelUpMoves>
		<!--Has 6 egg move(s)-->
		<EggMoves>
			<MoveID>19</MoveID>
			<MoveID>38</MoveID>
			<MoveID>88</MoveID>
			<MoveID>95</MoveID>
			<MoveID>267</MoveID>
			<MoveID>498</MoveID>
		</EggMoves>
		<!--Can learn 32 HM/TM move(s)-->
		<HmTmMoves>
			<MoveID>12</MoveID>
			<MoveID>24</MoveID>
			<MoveID>48</MoveID>
			<MoveID>56</MoveID>
			<MoveID>67</MoveID>
			<MoveID>104</MoveID>
			<MoveID>115</MoveID>
			<MoveID>134</MoveID>
			<MoveID>151</MoveID>
			<MoveID>153</MoveID>
			<MoveID>179</MoveID>
			<MoveID>197</MoveID>
			<MoveID>214</MoveID>
			<MoveID>223</MoveID>
			<MoveID>227</MoveID>
			<MoveID>232</MoveID>
			<MoveID>244</MoveID>
			<MoveID>263</MoveID>
			<MoveID>301</MoveID>
			<MoveID>304</MoveID>
			<MoveID>324</MoveID>
			<MoveID>326</MoveID>
			<MoveID>328</MoveID>
			<MoveID>331</MoveID>
			<MoveID>345</MoveID>
			<MoveID>360</MoveID>
			<MoveID>394</MoveID>
			<MoveID>471</MoveID>
			<MoveID>490</MoveID>
			<MoveID>509</MoveID>
			<MoveID>534</MoveID>
			<MoveID>539</MoveID>
		</HmTmMoves>
	</Moveset>
	<!--Moveset from waza_p2.bin-->
	<Moveset>
		<!--Learns 13 move(s)-->
		<LevelUpMoves>
			<Learn>
				<Level>1</Level>
				<MoveID>174</MoveID>
			</Learn>
			<Learn>
				<Level>1</Level>
				<MoveID>217</MoveID>
			</Learn>
			<Learn>
				<Level>5</Level>
				<MoveID>46</MoveID>
			</Learn>
			<Learn>
				<Level>9</Level>
				<MoveID>34</MoveID>
			</Learn>
			<Learn>
				<Level>13</Level>
				<MoveID>311</MoveID>
			</Learn>
			<Learn>
				<Level>18</Level>
				<MoveID>134</MoveID>
			</Learn>
			<Learn>
				<Level>23</Level>
				<MoveID>130</MoveID>
			</Learn>
			<Learn>
				<Level>28</Level>
				<MoveID>203</MoveID>
			</Learn>
			<Learn>
				<Level>32</Level>
				<MoveID>471</MoveID>
			</Learn>
			<Learn>
				<Level>36</Level>
				<MoveID>40</MoveID>
			</Learn>
			<Learn>
				<Level>40</Level>
				<MoveID>339</MoveID>
			</Learn>
			<Learn>
				<Level>45</Level>
				<MoveID>539</MoveID>
			</Learn>
			<Learn>
				<Level>50</Level>
				<MoveID>293</MoveID>
			</Learn>
		</LevelUpMoves>
		<!--Has 6 egg move(s)-->
		<EggMoves>
			<MoveID>19</MoveID>
			<MoveID>38</MoveID>
			<MoveID>88</MoveID>
			<MoveID>95</MoveID>
			<MoveID>267</MoveID>
			<MoveID>498</MoveID>
		</EggMoves>
		<!--Can learn 32 HM/TM move(s)-->
		<HmTmMoves>
			<MoveID>12</MoveID>
			<MoveID>24</MoveID>
			<MoveID>48</MoveID>
			<MoveID>56</MoveID>
			<MoveID>67</MoveID>
			<MoveID>104</MoveID>
			<MoveID>115</MoveID>
			<MoveID>134</MoveID>
			<MoveID>151</MoveID>
			<MoveID>153</MoveID>
			<MoveID>179</MoveID>
			<MoveID>197</MoveID>
			<MoveID>214</MoveID>
			<MoveID>223</MoveID>
			<MoveID>227</MoveID>
			<MoveID>232</MoveID>
			<MoveID>244</MoveID>
			<MoveID>263</MoveID>
			<MoveID>301</MoveID>
			<MoveID>304</MoveID>
			<MoveID>324</MoveID>
			<MoveID>326</MoveID>
			<MoveID>328</MoveID>
			<MoveID>331</MoveID>
			<MoveID>345</MoveID>
			<MoveID>360</MoveID>
			<MoveID>394</MoveID>
			<MoveID>471</MoveID>
			<MoveID>490</MoveID>
			<MoveID>509</MoveID>
			<MoveID>534</MoveID>
			<MoveID>539</MoveID>
		</HmTmMoves>
	</Moveset>
	<!--Stats growth and exp requirements-->
	<StatsGrowth>
		<!--Level 1-->
		<Level>
			<RequiredExp>0</RequiredExp>
			<HP>0</HP>
			<Attack>0</Attack>
			<SpAttack>0</SpAttack>
			<Defense>0</Defense>
			<SpDefense>0</SpDefense>
		</Level>
		<!--Level 2-->
		<Level>
			<RequiredExp>8</RequiredExp>
			<HP>1</HP>
			<Attack>1</Attack>
			<SpAttack>1</SpAttack>
			<Defense>1</Defense>
			<SpDefense>1</SpDefense>
		</Level>
		<!--Level 3-->
		<Level>
			<RequiredExp>21</RequiredExp>
			<HP>2</HP>
			<Attack>2</Attack>
			<SpAttack>2</SpAttack>
			<Defense>0</Defense>
			<SpDefense>0</SpDefense>
		</Level>
		<!--Level 4-->
		<Level>
			<RequiredExp>36</RequiredExp>
			<HP>1</HP>
			<Attack>0</Attack>
			<SpAttack>0</SpAttack>
			<Defense>2</Defense>
			<SpDefense>2</SpDefense>
		</Level>
		<!--Level 5-->
		<Level>
			<RequiredExp>80</RequiredExp>
			<HP>2</HP>
			<Attack>2</Attack>
			<SpAttack>2</SpAttack>
			<Defense>0</Defense>
			<SpDefense>0</SpDefense>
		</Level>
		<!--Level 6-->
		<Level>
			<RequiredExp>175</RequiredExp>
			<HP>1</HP>
			<Attack>0</Attack>
			<SpAttack>0</SpAttack>
			<Defense>2</Defense>
			<SpDefense>2</SpDefense>
		</Level>
		<!--Level 7-->
		<Level>
			<RequiredExp>272</RequiredExp>
			<HP>2</HP>
			<Attack>2</Attack>
			<SpAttack>2</SpAttack>
			<Defense>0</Defense>
			<SpDefense>0</SpDefense>
		</Level>
		<!--Level 8-->
		<Level>
			<RequiredExp>510</RequiredExp>
			<HP>1</HP>
			<Attack>1</Attack>
			<SpAttack>1</SpAttack>
			<Defense>2</Defense>
			<SpDefense>2</SpDefense>
		</Level>
		<!--Level 9-->
		<Level>
			<RequiredExp>1028</RequiredExp>
			<HP>2</HP>
			<Attack>2</Attack>
			<SpAttack>2</SpAttack>
			<Defense>0</Defense>
			<SpDefense>0</SpDefense>
		</Level>
		<!--Level 10-->
		<Level>
			<RequiredExp>1549</RequiredExp>
			<HP>1</HP>
			<Attack>1</Attack>
			<SpAttack>1</SpAttack>
			<Defense>2</Defense>
			<SpDefense>2</SpDefense>
		</Level>
		<!--Level 11-->
		<Level>
			<RequiredExp>2369</RequiredExp>
			<HP>2</HP>
			<Attack>2</Attack>
			<SpAttack>2</SpAttack>
			<Defense>0</Defense>
			<SpDefense>0</SpDefense>
		</Level>
		<!--Level 12-->
		<Level>
			<RequiredExp>4371</RequiredExp>
			<HP>1</HP>
			<Attack>1</Attack>
			<SpAttack>1</SpAttack>
			<Defense>2</Defense>
			<SpDefense>2</SpDefense>
		</Level>
		<!--Level 13-->
		<Level>
			<RequiredExp>6379</RequiredExp>
			<HP>2</HP>
			<Attack>2</Attack>
			<SpAttack>2</SpAttack>
			<Defense>0</Defense>
			<SpDefense>0</SpDefense>
		</Level>
		<!--Level 14-->
		<Level>
			<RequiredExp>9945</RequiredExp>
			<HP>1</HP>
			<Attack>1</Attack>
			<SpAttack>1</SpAttack>
			<Defense>0</Defense>
			<SpDefense>0</SpDefense>
		</Level>
		<!--Level 15-->
		<Level>
			<RequiredExp>13515</RequiredExp>
			<HP>2</HP>
			<Attack>2</Attack>
			<SpAttack>2</SpAttack>
			<Defense>1</Defense>
			<SpDefense>1</SpDefense>
		</Level>
		<!--Level 16-->
		<Level>
			<RequiredExp>17517</RequiredExp>
			<HP>1</HP>
			<Attack>1</Attack>
			<SpAttack>1</SpAttack>
			<Defense>1</Defense>
			<SpDefense>1</SpDefense>
		</Level>
		<!--Level 17-->
		<Level>
			<RequiredExp>21524</RequiredExp>
			<HP>2</HP>
			<Attack>2</Attack>
			<SpAttack>2</SpAttack>
			<Defense>0</Defense>
			<SpDefense>0</SpDefense>
		</Level>
		<!--Level 18-->
		<Level>
			<RequiredExp>25974</RequiredExp>
			<HP>1</HP>
			<Attack>1</Attack>
			<SpAttack>1</SpAttack>
			<Defense>1</Defense>
			<SpDefense>1</SpDefense>
		</Level>
		<!--Level 19-->
		<Level>
			<RequiredExp>30427</RequiredExp>
			<HP>2</HP>
			<Attack>3</Attack>
			<SpAttack>3</SpAttack>
			<Defense>3</Defense>
			<SpDefense>3</SpDefense>
		</Level>
		<!--Level 20-->
		<Level>
			<RequiredExp>34883</RequiredExp>
			<HP>2</HP>
			<Attack>3</Attack>
			<SpAttack>3</SpAttack>
			<Defense>3</Defense>
			<SpDefense>3</SpDefense>
		</Level>
		<!--Level 21-->
		<Level>
			<RequiredExp>39373</RequiredExp>
			<HP>2</HP>
			<Attack>3</Attack>
			<SpAttack>3</SpAttack>
			<Defense>3</Defense>
			<SpDefense>2</SpDefense>
		</Level>
		<!--Level 22-->
		<Level>
			<RequiredExp>44574</RequiredExp>
			<HP>2</HP>
			<Attack>3</Attack>
			<SpAttack>3</SpAttack>
			<Defense>3</Defense>
			<SpDefense>2</SpDefense>
		</Level>
		<!--Level 23-->
		<Level>
			<RequiredExp>49780</RequiredExp>
			<HP>2</HP>
			<Attack>3</Attack>
			<SpAttack>1</SpAttack>
			<Defense>2</Defense>
			<SpDefense>2</SpDefense>
		</Level>
		<!--Level 24-->
		<Level>
			<RequiredExp>54991</RequiredExp>
			<HP>1</HP>
			<Attack>1</Attack>
			<SpAttack>1</SpAttack>
			<Defense>1</Defense>
			<SpDefense>2</SpDefense>
		</Level>
		<!--Level 25-->
		<Level>
			<RequiredExp>61627</RequiredExp>
			<HP>2</HP>
			<Attack>1</Attack>
			<SpAttack>1</SpAttack>
			<Defense>0</Defense>
			<SpDefense>0</SpDefense>
		</Level>
		<!--Level 26-->
		<Level>
			<RequiredExp>69701</RequiredExp>
			<HP>1</HP>
			<Attack>1</Attack>
			<SpAttack>1</SpAttack>
			<Defense>1</Defense>
			<SpDefense>1</SpDefense>
		</Level>
		<!--Level 27-->
		<Level>
			<RequiredExp>78485</RequiredExp>
			<HP>2</HP>
			<Attack>1</Attack>
			<SpAttack>1</SpAttack>
			<Defense>0</Defense>
			<SpDefense>0</SpDefense>
		</Level>
		<!--Level 28-->
		<Level>
			<RequiredExp>87981</RequiredExp>
			<HP>1</HP>
			<Attack>1</Attack>
			<SpAttack>1</SpAttack>
			<Defense>1</Defense>
			<SpDefense>1</SpDefense>
		</Level>
		<!--Level 29-->
		<Level>
			<RequiredExp>98189</RequiredExp>
			<HP>2</HP>
			<Attack>1</Attack>
			<SpAttack>1</SpAttack>
			<Defense>0</Defense>
			<SpDefense>0</SpDefense>
		</Level>
		<!--Level 30-->
		<Level>
			<RequiredExp>109108</RequiredExp>
			<HP>1</HP>
			<Attack>1</Attack>
			<SpAttack>1</SpAttack>
			<Defense>0</Defense>
			<SpDefense>0</SpDefense>
		</Level>
		<!--Level 31-->
		<Level>
			<RequiredExp>120739</RequiredExp>
			<HP>2</HP>
			<Attack>1</Attack>
			<SpAttack>1</SpAttack>
			<Defense>1</Defense>
			<SpDefense>1</SpDefense>
		</Level>
		<!--Level 32-->
		<Level>
			<RequiredExp>133082</RequiredExp>
			<HP>1</HP>
			<Attack>1</Attack>
			<SpAttack>1</SpAttack>
			<Defense>0</Defense>
			<SpDefense>0</SpDefense>
		</Level>
		<!--Level 33-->
		<Level>
			<RequiredExp>147571</RequiredExp>
			<HP>2</HP>
			<Attack>1</Attack>
			<SpAttack>1</SpAttack>
			<Defense>1</Defense>
			<SpDefense>1</SpDefense>
		</Level>
		<!--Level 34-->
		<Level>
			<RequiredExp>162771</RequiredExp>
			<HP>1</HP>
			<Attack>1</Attack>
			<SpAttack>1</SpAttack>
			<Defense>1</Defense>
			<SpDefense>1</SpDefense>
		</Level>
		<!--Level 35-->
		<Level>
			<RequiredExp>178682</RequiredExp>
			<HP>2</HP>
			<Attack>1</Attack>
			<SpAttack>1</SpAttack>
			<Defense>0</Defense>
			<SpDefense>0</SpDefense>
		</Level>
		<!--Level 36-->
		<Level>
			<RequiredExp>195305</RequiredExp>
			<HP>1</HP>
			<Attack>1</Attack>
			<SpAttack>1</SpAttack>
			<Defense>1</Defense>
			<SpDefense>1</SpDefense>
		</Level>
		<!--Level 37-->
		<Level>
			<RequiredExp>212640</RequiredExp>
			<HP>2</HP>
			<Attack>1</Attack>
			<SpAttack>1</SpAttack>
			<Defense>0</Defense>
			<SpDefense>0</SpDefense>
		</Level>
		<!--Level 38-->
		<Level>
			<RequiredExp>230686</RequiredExp>
			<HP>1</HP>
			<Attack>1</Attack>
			<SpAttack>1</SpAttack>
			<Defense>1</Defense>
			<SpDefense>1</SpDefense>
		</Level>
		<!--Level 39-->
		<Level>
			<RequiredExp>249444</RequiredExp>
			<HP>2</HP>
			<Attack>1</Attack>
			<SpAttack>1</SpAttack>
			<Defense>1</Defense>
			<SpDefense>1</SpDefense>
		</Level>
		<!--Level 40-->
		<Level>
			<RequiredExp>268913</RequiredExp>
			<HP>1</HP>
			<Attack>0</Attack>
			<SpAttack>1</SpAttack>
			<Defense>0</Defense>
			<SpDefense>1</SpDefense>
		</Level>
		<!--Level 41-->
		<Level>
			<RequiredExp>289095</RequiredExp>
			<HP>0</HP>
			<Attack>1</Attack>
			<SpAttack>0</SpAttack>
			<Defense>1</Defense>
			<SpDefense>0</SpDefense>
		</Level>
		<!--Level 42-->
		<Level>
			<RequiredExp>309988</RequiredExp>
			<HP>1</HP>
			<Attack>0</Attack>
			<SpAttack>1</SpAttack>
			<Defense>0</Defense>
			<SpDefense>1</SpDefense>
		</Level>
		<!--Level 43-->
		<Level>
			<RequiredExp>331592</RequiredExp>
			<HP>0</HP>
			<Attack>1</Attack>
			<SpAttack>0</SpAttack>
			<Defense>1</Defense>
			<SpDefense>0</SpDefense>
		</Level>
		<!--Level 44-->
		<Level>
			<RequiredExp>354619</RequiredExp>
			<HP>1</HP>
			<Attack>0</Attack>
			<SpAttack>1</SpAttack>
			<Defense>0</Defense>
			<SpDefense>1</SpDefense>
		</Level>
		<!--Level 45-->
		<Level>
			<RequiredExp>379071</RequiredExp>
			<HP>0</HP>
			<Attack>1</Attack>
			<SpAttack>0</SpAttack>
			<Defense>1</Defense>
			<SpDefense>0</SpDefense>
		</Level>
		<!--Level 46-->
		<Level>
			<RequiredExp>404944</RequiredExp>
			<HP>1</HP>
			<Attack>0</Attack>
			<SpAttack>1</SpAttack>
			<Defense>0</Defense>
			<SpDefense>1</SpDefense>
		</Level>
		<!--Level 47-->
		<Level>
			<RequiredExp>432241</RequiredExp>
			<HP>0</HP>
			<Attack>1</Attack>
			<SpAttack>0</SpAttack>
			<Defense>1</Defense>
			<SpDefense>0</SpDefense>
		</Level>
		<!--Level 48-->
		<Level>
			<RequiredExp>460962</RequiredExp>
			<HP>1</HP>
			<Attack>0</Attack>
			<SpAttack>1</SpAttack>
			<Defense>0</Defense>
			<SpDefense>1</SpDefense>
		</Level>
		<!--Level 49-->
		<Level>
			<RequiredExp>491106</RequiredExp>
			<HP>0</HP>
			<Attack>1</Attack>
			<SpAttack>0</SpAttack>
			<Defense>1</Defense>
			<SpDefense>0</SpDefense>
		</Level>
		<!--Level 50-->
		<Level>
			<RequiredExp>522673</RequiredExp>
			<HP>1</HP>
			<Attack>0</Attack>
			<SpAttack>1</SpAttack>
			<Defense>0</Defense>
			<SpDefense>1</SpDefense>
		</Level>
		<!--Level 51-->
		<Level>
			<RequiredExp>555663</RequiredExp>
			<HP>0</HP>
			<Attack>1</Attack>
			<SpAttack>0</SpAttack>
			<Defense>1</Defense>
			<SpDefense>0</SpDefense>
		</Level>
		<!--Level 52-->
		<Level>
			<RequiredExp>590077</RequiredExp>
			<HP>1</HP>
			<Attack>0</Attack>
			<SpAttack>1</SpAttack>
			<Defense>0</Defense>
			<SpDefense>1</SpDefense>
		</Level>
		<!--Level 53-->
		<Level>
			<RequiredExp>625665</RequiredExp>
			<HP>0</HP>
			<Attack>1</Attack>
			<SpAttack>0</SpAttack>
			<Defense>1</Defense>
			<SpDefense>0</SpDefense>
		</Level>
		<!--Level 54-->
		<Level>
			<RequiredExp>661260</RequiredExp>
			<HP>1</HP>
			<Attack>0</Attack>
			<SpAttack>1</SpAttack>
			<Defense>0</Defense>
			<SpDefense>1</SpDefense>
		</Level>
		<!--Level 55-->
		<Level>
			<RequiredExp>696862</RequiredExp>
			<HP>0</HP>
			<Attack>1</Attack>
			<SpAttack>0</SpAttack>
			<Defense>1</Defense>
			<SpDefense>0</SpDefense>
		</Level>
		<!--Level 56-->
		<Level>
			<RequiredExp>732471</RequiredExp>
			<HP>1</HP>
			<Attack>0</Attack>
			<SpAttack>1</SpAttack>
			<Defense>0</Defense>
			<SpDefense>1</SpDefense>
		</Level>
		<!--Level 57-->
		<Level>
			<RequiredExp>768088</RequiredExp>
			<HP>0</HP>
			<Attack>1</Attack>
			<SpAttack>0</SpAttack>
			<Defense>1</Defense>
			<SpDefense>0</SpDefense>
		</Level>
		<!--Level 58-->
		<Level>
			<RequiredExp>803711</RequiredExp>
			<HP>1</HP>
			<Attack>0</Attack>
			<SpAttack>1</SpAttack>
			<Defense>0</Defense>
			<SpDefense>1</SpDefense>
		</Level>
		<!--Level 59-->
		<Level>
			<RequiredExp>839341</RequiredExp>
			<HP>0</HP>
			<Attack>1</Attack>
			<SpAttack>0</SpAttack>
			<Defense>1</Defense>
			<SpDefense>0</SpDefense>
		</Level>
		<!--Level 60-->
		<Level>
			<RequiredExp>874979</RequiredExp>
			<HP>1</HP>
			<Attack>1</Attack>
			<SpAttack>1</SpAttack>
			<Defense>1</Defense>
			<SpDefense>1</SpDefense>
		</Level>
		<!--Level 61-->
		<Level>
			<RequiredExp>910624</RequiredExp>
			<HP>1</HP>
			<Attack>1</Attack>
			<SpAttack>1</SpAttack>
			<Defense>1</Defense>
			<SpDefense>1</SpDefense>
		</Level>
		<!--Level 62-->
		<Level>
			<RequiredExp>946275</RequiredExp>
			<HP>1</HP>
			<Attack>1</Attack>
			<SpAttack>1</SpAttack>
			<Defense>1</Defense>
			<SpDefense>1</SpDefense>
		</Level>
		<!--Level 63-->
		<Level>
			<RequiredExp>981934</RequiredExp>
			<HP>1</HP>
			<Attack>1</Attack>
			<SpAttack>1</SpAttack>
			<Defense>1</Defense>
			<SpDefense>1</SpDefense>
		</Level>
		<!--Level 64-->
		<Level>
			<RequiredExp>1017601</RequiredExp>
			<HP>1</HP>
			<Attack>1</Attack>
			<SpAttack>1</SpAttack>
			<Defense>1</Defense>
			<SpDefense>1</SpDefense>
		</Level>
		<!--Level 65-->
		<Level>
			<RequiredExp>1053274</RequiredExp>
			<HP>1</HP>
			<Attack>1</Attack>
			<SpAttack>1</SpAttack>
			<Defense>1</Defense>
			<SpDefense>1</SpDefense>
		</Level>
		<!--Level 66-->
		<Level>
			<RequiredExp>1088954</RequiredExp>
			<HP>1</HP>
			<Attack>1</Attack>
			<SpAttack>1</SpAttack>
			<Defense>1</Defense>
			<SpDefense>1</SpDefense>
		</Level>
		<!--Level 67-->
		<Level>
			<RequiredExp>1124642</RequiredExp>
			<HP>1</HP>
			<Attack>1</Attack>
			<SpAttack>1</SpAttack>
			<Defense>1</Defense>
			<SpDefense>1</SpDefense>
		</Level>
		<!--Level 68-->
		<Level>
			<RequiredExp>1160336</RequiredExp>
			<HP>1</HP>
			<Attack>1</Attack>
			<SpAttack>1</SpAttack>
			<Defense>1</Defense>
			<SpDefense>1</SpDefense>
		</Level>
		<!--Level 69-->
		<Level>
			<RequiredExp>1196038</RequiredExp>
			<HP>1</HP>
			<Attack>1</Attack>
			<SpAttack>1</SpAttack>
			<Defense>1</Defense>
			<SpDefense>1</SpDefense>
		</Level>
		<!--Level 70-->
		<Level>
			<RequiredExp>1231747</RequiredExp>
			<HP>1</HP>
			<Attack>1</Attack>
			<SpAttack>1</SpAttack>
			<Defense>1</Defense>
			<SpDefense>1</SpDefense>
		</Level>
		<!--Level 71-->
		<Level>
			<RequiredExp>1267463</RequiredExp>
			<HP>1</HP>
			<Attack>1</Attack>
			<SpAttack>1</SpAttack>
			<Defense>1</Defense>
			<SpDefense>1</SpDefense>
		</Level>
		<!--Level 72-->
		<Level>
			<RequiredExp>1303186</RequiredExp>
			<HP>1</HP>
			<Attack>1</Attack>
			<SpAttack>1</SpAttack>
			<Defense>1</Defense>
			<SpDefense>1</SpDefense>
		</Level>
		<!--Level 73-->
		<Level>
			<RequiredExp>1338916</RequiredExp>
			<HP>1</HP>
			<Attack>1</Attack>
			<SpAttack>1</SpAttack>
			<Defense>1</Defense>
			<SpDefense>1</SpDefense>
		</Level>
		<!--Level 74-->
		<Level>
			<RequiredExp>1374654</RequiredExp>
			<HP>1</HP>
			<Attack>1</Attack>
			<SpAttack>1</SpAttack>
			<Defense>1</Defense>
			<SpDefense>1</SpDefense>
		</Level>
		<!--Level 75-->
		<Level>
			<RequiredExp>1410398</RequiredExp>
			<HP>1</HP>
			<Attack>1</Attack>
			<SpAttack>1</SpAttack>
			<Defense>1</Defense>
			<SpDefense>1</SpDefense>
		</Level>
		<!--Level 76-->
		<Level>
			<RequiredExp>1446149</RequiredExp>
			<HP>1</HP>
			<Attack>1</Attack>
			<SpAttack>1</SpAttack>
			<Defense>1</Defense>
			<SpDefense>1</SpDefense>
		</Level>
		<!--Level 77-->
		<Level>
			<RequiredExp>1481908</RequiredExp>
			<HP>1</HP>
			<Attack>1</Attack>
			<SpAttack>1</SpAttack>
			<Defense>1</Defense>
			<SpDefense>1</SpDefense>
		</Level>
		<!--Level 78-->
		<Level>
			<RequiredExp>1517674</RequiredExp>
			<HP>1</HP>
			<Attack>1</Attack>
			<SpAttack>1</SpAttack>
			<Defense>1</Defense>
			<SpDefense>1</SpDefense>
		</Level>
		<!--Level 79-->
		<Level>
			<RequiredExp>1553447</RequiredExp>
			<HP>1</HP>
			<Attack>1</Attack>
			<SpAttack>1</SpAttack>
			<Defense>1</Defense>
			<SpDefense>1</SpDefense>
		</Level>
		<!--Level 80-->
		<Level>
			<RequiredExp>1589227</RequiredExp>
			<HP>1</HP>
			<Attack>1</Attack>
			<SpAttack>1</SpAttack>
			<Defense>1</Defense>
			<SpDefense>1</SpDefense>
		</Level>
		<!--Level 81-->
		<Level>
			<RequiredExp>1625014</RequiredExp>
			<HP>1</HP>
			<Attack>1</Attack>
			<SpAttack>1</SpAttack>
			<Defense>1</Defense>
			<SpDefense>1</SpDefense>
		</Level>
		<!--Level 82-->
		<Level>
			<RequiredExp>1660808</RequiredExp>
			<HP>1</HP>
			<Attack>1</Attack>
			<SpAttack>1</SpAttack>
			<Defense>1</Defense>
			<SpDefense>1</SpDefense>
		</Level>
		<!--Level 83-->
		<Level>
			<RequiredExp>1696609</RequiredExp>
			<HP>1</HP>
			<Attack>1</Attack>
			<SpAttack>1</SpAttack>
			<Defense>1</Defense>
			<SpDefense>1</SpDefense>
		</Level>
		<!--Level 84-->
		<Level>
			<RequiredExp>1732418</RequiredExp>
			<HP>1</HP>
			<Attack>1</Attack>
			<SpAttack>1</SpAttack>
			<Defense>1</Defense>
			<SpDefense>1</SpDefense>
		</Level>
		<!--Level 85-->
		<Level>
			<RequiredExp>1768234</RequiredExp>
			<HP>1</HP>
			<Attack>1</Attack>
			<SpAttack>1</SpAttack>
			<Defense>1</Defense>
			<SpDefense>1</SpDefense>
		</Level>
		<!--Level 86-->
		<Level>
			<RequiredExp>1804056</RequiredExp>
			<HP>1</HP>
			<Attack>1</Attack>
			<SpAttack>1</SpAttack>
			<Defense>1</Defense>
			<SpDefense>1</SpDefense>
		</Level>
		<!--Level 87-->
		<Level>
			<RequiredExp>1839886</RequiredExp>
			<HP>1</HP>
			<Attack>1</Attack>
			<SpAttack>1</SpAttack>
			<Defense>1</Defense>
			<SpDefense>1</SpDefense>
		</Level>
		<!--Level 88-->
		<Level>
			<RequiredExp>1875723</RequiredExp>
			<HP>1</HP>
			<Attack>1</Attack>
			<SpAttack>1</SpAttack>
			<Defense>1</Defense>
			<SpDefense>1</SpDefense>
		</Level>
		<!--Level 89-->
		<Level>
			<RequiredExp>1911567</RequiredExp>
			<HP>1</HP>
			<Attack>1</Attack>
			<SpAttack>1</SpAttack>
			<Defense>1</Defense>
			<SpDefense>1</SpDefense>
		</Level>
		<!--Level 90-->
		<Level>
			<RequiredExp>1947418</RequiredExp>
			<HP>1</HP>
			<Attack>1</Attack>
			<SpAttack>1</SpAttack>
			<Defense>1</Defense>
			<SpDefense>1</SpDefense>
		</Level>
		<!--Level 91-->
		<Level>
			<RequiredExp>1983276</RequiredExp>
			<HP>1</HP>
			<Attack>1</Attack>
			<SpAttack>1</SpAttack>
			<Defense>1</Defense>
			<SpDefense>1</SpDefense>
		</Level>
		<!--Level 92-->
		<Level>
			<RequiredExp>2019142</RequiredExp>
			<HP>1</HP>
			<Attack>1</Attack>
			<SpAttack>1</SpAttack>
			<Defense>1</Defense>
			<SpDefense>1</SpDefense>
		</Level>
		<!--Level 93-->
		<Level>
			<RequiredExp>2055014</RequiredExp>
			<HP>1</HP>
			<Attack>1</Attack>
			<SpAttack>1</SpAttack>
			<Defense>1</Defense>
			<SpDefense>1</SpDefense>
		</Level>
		<!--Level 94-->
		<Level>
			<RequiredExp>2090894</RequiredExp>
			<HP>1</HP>
			<Attack>1</Attack>
			<SpAttack>1</SpAttack>
			<Defense>1</Defense>
			<SpDefense>1</SpDefense>
		</Level>
		<!--Level 95-->
		<Level>
			<RequiredExp>2126781</RequiredExp>
			<HP>1</HP>
			<Attack>1</Attack>
			<SpAttack>1</SpAttack>
			<Defense>1</Defense>
			<SpDefense>1</SpDefense>
		</Level>
		<!--Level 96-->
		<Level>
			<RequiredExp>2162674</RequiredExp>
			<HP>1</HP>
			<Attack>1</Attack>
			<SpAttack>1</SpAttack>
			<Defense>1</Defense>
			<SpDefense>1</SpDefense>
		</Level>
		<!--Level 97-->
		<Level>
			<RequiredExp>2198575</RequiredExp>
			<HP>1</HP>
			<Attack>1</Attack>
			<SpAttack>1</SpAttack>
			<Defense>1</Defense>
			<SpDefense>1</SpDefense>
		</Level>
		<!--Level 98-->
		<Level>
			<RequiredExp>2234483</RequiredExp>
			<HP>1</HP>
			<Attack>1</Attack>
			<SpAttack>1</SpAttack>
			<Defense>1</Defense>
			<SpDefense>1</SpDefense>
		</Level>
		<!--Level 99-->
		<Level>
			<RequiredExp>2270399</RequiredExp>
			<HP>1</HP>
			<Attack>1</Attack>
			<SpAttack>1</SpAttack>
			<Defense>1</Defense>
			<SpDefense>1</SpDefense>
		</Level>
		<!--Level 100-->
		<Level>
			<RequiredExp>2306363</RequiredExp>
			<HP>1</HP>
			<Attack>1</Attack>
			<SpAttack>1</SpAttack>
			<Defense>1</Defense>
			<SpDefense>1</SpDefense>
		</Level>
	</StatsGrowth>
</Pokemon>
